Workbook
Name postcode: #REF!
Name postcode2: #REF!
Name Postcodes: 'Postal Codes 1'!$B$2:$C$1540
Name ProductName: 'Task 4.4'!#REF!
Name ProductName: 'Task 4.3'!$R$4:$U$13
Name test: 'Postal Codes 1'!$B$1:$C$1540

Sheet Task 4.0
A1: ID | B1: First Name | C1: Last Name | D1: Title | E1: Gender | F1: Credit | G1: Street | H1: Town | I1: Order Date | J1: Quantity | K1: Product
A2: 1 | B2: Nanci | C2: Camp | D2: Mrs | E2: F | F2: 60 | G2: Rosmore Road | H2: Berkeley | I2: 39988 | J2: 13 | K2: A1 | M2: STEPS
A3: 2 | B3: Erlinda | C3: Dorsey | D3: Mrs | E3: F | F3: 90 | G3: Roxwell Road | H3: Glossop | I3: 39770 | J3: 14 | K3: C3 | M3: Imported the data from the Access database file named "Portfolio4.accdb" using Data Menu
A4: 3 | B4: Albertha | C4: Devine | D4: Mrs | E4: F | F4: 60 | G4: Ashbury Place | H4: Immingham | I4: 39895 | J4: 23 | K4: E
A5: 4 | B5: Nathalie | C5: Washington | D5: Miss | E5: F | F5: 60 | G5: Grafton Road | H5: Broadstone | I5: 39830 | J5: 79 | K5: E | M5: Formatted the columns in the worksheet (width, number format, etc.)
A6: 5 | B6: Shonta | C6: Hedrick | D6: Miss | E6: fem | F6: 60 | G6: Beechdale Road | H6: Port Talbot | I6: 39988 | J6: 44 | K6: C3
A7: 6 | B7: Veronika | C7: Lundy | D7: Miss | E7: F | F7: 90 | G7: Katherine Gardens | H7: Ardgay | I7: 40316 | J7: 37 | K7: A3 | M7: Note: This Sheet is Password Protected, To unlock this sheet use "qwer" as password
A8: 7 | B8: Valeria | C8: Frost | D8: Mrs | E8: F | F8: 30 | G8: Ross Way | H8: Solihull | I8: 40202 | J8: 12 | K8: C2
A9: 8 | B9: Randa | C9: Woods | D9: Mrs | E9: F | F9: 30 | G9: Artisans Dwellings | H9: Tring | I9: 40497 | J9: 55 | K9: C1
A10: 9 | B10: Karole | C10: Navarro | D10: Mrs | E10: F | F10: 30 | G10: Rhoda Street | H10: St. Ives | I10: 39938 | J10: 10 | K10: C3
A11: 10 | B11: Martin | C11: Anthony | D11: Miss | E11: F | F11: 90 | G11: Iceland Road | H11: Campbeltown | I11: 40466 | J11: 76 | K11: A2
A12: 11 | B12: Shanae | C12: Roland | D12: Mrs | E12: F | F12: 90 | G12: Samels Court | H12: Newbridge | I12: 40031 | J12: 28 | K12: C2
A13: 12 | B13: Yen | C13: Culver | D13: Miss | E13: F | F13: 60 | G13: Garratt Green | H13: London | I13: 39965 | J13: 41 | K13: A2
A14: 13 | B14: Monica | C14: Doran | D14: Miss | E14: F | F14: 90 | G14: High St | H14: Caldicot | I14: 39516 | J14: 48 | K14: B
A15: 14 | B15: Laureen | C15: Richards | D15: Prof | E15: F | F15: 90 | G15: Brackenfield Close | H15: Broseley | I15: 39665 | J15: 34 | K15: C4
A16: 15 | B16: Meta | C16: Wright | D16: Mrs | E16: F | F16: 60 | G16: Bearstead Rise | H16: Y Felinheli | I16: 40337 | J16: 57 | K16: C4
A17: 16 | B17: Bobbye | C17: Vasquez | D17: Mrs | E17: F | F17: 30 | G17: Baker Road | H17: Trowbridge | I17: 40532 | J17: 59 | K17: E
A18: 17 | B18: Emily | C18: Butler | D18: Miss | E18: F | F18: 30 | G18: Telford Close | H18: Isles Of Scilly | I18: 40271 | J18: 84 | K18: C1
A19: 18 | B19: Iona | C19: Hutchinson | D19: Ms | E19: F | F19: 30 | G19: Queens Buildings | H19: Kilmacolm | I19: 40183 | J19: 39 | K19: C4
... A95: 94 | B95: Waneta | C95: Klein | D95: Miss | E95: F | F95: 60 | G95: Kidd Place | H95: Strathdon | I95: 39833 | J95: 97 | K95: C3
A96: 95 | B96: Jadwiga | C96: Contreras | E96: F | F96: 90 | G96: Little Lemon | H96: Llanrwst | I96: 40064 | J96: 24 | K96: E
A97: 96 | B97: Catherina | C97: Galvan | D97: Ms | E97: F | F97: 60 | G97: Little New | H97: Darwen | I97: 39927 | J97: 87 | K97: A2
A98: 97 | B98: Leslie | C98: Hobson | D98: Mrs | E98: F | F98: 30 | G98: Templecombe Road | H98: Plockton | I98: 40500 | J98: 41 | K98: A2
A99: 98 | B99: Jona | C99: Mcneill | D99: Miss | E99: F | F99: 90 | G99: Warner Road | H99: Coleford | I99: 40312 | J99: 68 | K99: E
A100: 99 | B100: Phylis | C100: Starks | D100: Mrs | E100: F | F100: 30 | G100: Du Burstow | H100: Surrey | I100: 40037 | J100: 47 | K100: B
A101: 100 | B101: Chasidy | C101: Pittman | D101: Miss | E101: F | F101: 90 | G101: Vine Cottages | H101: Tewkesbury | I101: 40107 | J101: 51 | K101: C1
A102: 101 | B102: Rina | C102: Hayes | D102: Mrs | E102: F | F102: 60 | G102: Jamaica Level | H102: Buxton | I102: 40000 | J102: 97 | K102: B
A103: 102 | B103: Piedad | C103: Mcmullen | D103: Miss | E103: F | F103: 90 | G103: College Yard | H103: Colchester | I103: 40526 | J103: 70 | K103: C2
A104: 103 | B104: Wanda | C104: Eubanks | D104: Mrs | E104: F | F104: 90 | G104: Woodington Close | H104: Bushmills | I104: 39760 | J104: 83 | K104: E
A105: 104 | B105: Taunya | C105: Medeiros | D105: Miss | E105: F | F105: 60 | G105: Westmoreland Mews | H105: Ross-Shire | I105: 39862 | J105: 63 | K105: A2
A106: 105 | B106: Carla | C106: Grover | D106: Mrs | E106: F | F106: 60 | G106: Deepdene Close | H106: Wotton-Under-Edge | I106: 39523 | J106: 67 | K106: C2
A107: 106 | B107: Moon | C107: Cervantes | D107: Miss | E107: F | F107: 90 | G107: Broadbridge Close | H107: Sedbergh | I107: 39698 | J107: 65 | K107: A2
A108: 107 | B108: Christin | C108: Wolfe | D108: Mrs | E108: F | F108: 30 | G108: Christchurch Mews | H108: Wells-Next-The-Sea | I108: 40106 | J108: 45 | K108: E
... A212: 211 | B212: Rebbeca | C212: Middleton | D212: Miss | E212: F | F212: 30 | G212: Harberson Road | H212: Attleborough | I212: 40078 | J212: 63 | K212: A1
A213: 212 | B213: Paula | C213: Duke | D213: Mrs | E213: F | G213: Colonial House | H213: Ammanford | I213: 39786 | J213: 15 | K213: A3
A214: 213 | B214: Kristie | C214: Santos | D214: Miss | E214: F | F214: 90 | G214: Pembridge Crescent | H214: Portsmouth | I214: 39641 | J214: 82 | K214: A3
A215: 214 | B215: Bernarda | C215: Knutson | D215: Miss | E215: F | F215: 30 | G215: Searles Close | H215: Llanfyrnach | I215: 40340 | J215: 81 | K215: C1
A216: 215 | B216: Mandy | C216: York | D216: Mrs | E216: F | F216: 60 | G216: Beatrice Place | H216: Kinlochleven | I216: 40232 | J216: 50 | K216: A1
A217: 216 | B217: Francina | C217: Corley | D217: Miss | E217: F | F217: 90 | G217: Stewart Road | H217: Ventnor | J217: 55 | K217: C2
A218: 217 | B218: Evan | C218: Holmes | D218: Mrs | E218: F | F218: 60 | G218: Stanthorpe Close | H218: Helensburgh | I218: 40439 | J218: 72 | K218: C4
A219: 218 | B219: Julieann | C219: Numbers | D219: Miss | E219: F | F219: 60 | G219: Portman Gardens | H219: South Yorkshire | I219: 39516 | J219: 93 | K219: E
A220: 219 | B220: Francesca | C220: Neal | D220: Miss | E220: F | F220: 90 | G220: Friars Close | H220: Hawes | I220: 40146 | J220: 98 | K220: B
A221: 220 | B221: Priscila | C221: Sewell | D221: Ms | E221: F | F221: 30 | G221: Popes Lane | H221: Carnoustie | I221: 39909 | J221: 92 | K221: C2
A222: 221 | B222: Shakira | C222: Krueger | D222: Mrs | E222: F | F222: 90 | G222: Mutton Place | H222: Colne | I222: 39493 | J222: 10 | K222: C4
A223: 222 | B223: Cornelia | C223: Moreland | D223: Miss | E223: F | F223: 60 | G223: Thorndean Street | H223: Studley | I223: 40291 | J223: 27 | K223: A2
A224: 223 | B224: Lyndsey | C224: Neely | D224: Mrs | E224: F | F224: 30 | G224: Fardon Row | H224: Morecambe | I224: 40295 | J224: 28 | K224: D
A225: 224 | B225: Nettie | C225: Smiley | D225: Mrs | E225: F | F225: 30 | G225: Bedale Street | H225: Montgomery | I225: 40063 | J225: 30 | K225: C2
A226: 225 | B226: Ebony | C226: Simms | D226: Mrs | E226: F | F226: 30 | G226: Sussex Cottage | H226: Trowbridge | I226: 40064 | J226: 53 | K226: A1
A227: 226 | B227: Lilli | C227: Contreras | D227: Miss | E227: F | F227: 60 | G227: Claverley Grove | H227: Immingham | I227: 39523 | J227: 89 | K227: A2
A228: 227 | B228: Grisel | C228: Comer | D228: Mrs | E228: F | F228: 90 | G228: Talfourd Place | H228: North Humberside | I228: 39461 | J228: 22 | K228: C2
A229: 228 | B229: Lorinda | C229: Pate | D229: Miss | E229: F | F229: 90 | G229: Stock Street | H229: Bala | I229: 39775 | J229: 71 | K229: E
... A333: 332 | B333: Remedios | C333: Bolton | D333: Mrs | E333: F | F333: 90 | G333: Lion Yard | H333: Monmouth | I333: 39782 | J333: 65 | K333: A3
A334: 333 | B334: Lilian | C334: Schneider | D334: Miss | E334: F | F334: 60 | G334: Ponsonby Street | H334: Hastings | I334: 40286 | J334: 42
A335: 334 | B335: Karma | C335: Stahl | D335: Mrs | E335: F | F335: 30 | G335: Broomhouse Road | H335: Lynmouth | I335: 40340 | J335: 36 | K335: A2
A336: 335 | B336: Irmgard | C336: Askew | D336: Mrs | E336: F | F336: 30 | G336: Dudley Villas | H336: Buckley | I336: 39785 | J336: 27 | K336: A2
A337: 336 | B337: Yan | C337: Alford | D337: Mrs | E337: F | F337: 60 | G337: Thurlestone Avenue | H337: Eastbourne | I337: 39700 | J337: 86 | K337: A2
A338: 337 | B338: Felecia | C338: Rose | D338: Mrs | E338: F | F338: 60 | G338: Copleston Mews | H338: Broxbourne | I338: 40228 | J338: 26 | K338: A3
A339: 338 | B339: Loreen | C339: Boykin | D339: Mrs | E339: F | F339: 60 | G339: Northburgh Street | H339: Sheerness | I339: 40445 | J339: 78 | K339: A3
A340: 339 | B340: Ranee | C340: Herndon | D340: Miss | E340: F | F340: 60 | G340: Brunswick Industrial | H340: Cullompton | I340: 39697 | J340: 84 | K340: D
A341: 340 | B341: Sena | C341: Bass | D341: Miss | E341: F | F341: 60 | G341: Lansdowne Walk | H341: South Yorkshire | I341: 40076 | J341: 65 | K341: D
A342: 341 | B342: Annmarie | C342: Hearn | D342: Dr | E342: F | F342: 90 | G342: Brent Park | H342: Penrhyndeudraeth | I342: 40161 | J342: 82 | K342: E
A343: 342 | B343: Eileen | C343: Walden | D343: Miss | E343: F | F343: 90 | G343: Newmarket Terrace | H343: Brandon | I343: 39971 | J343: 37 | K343: A1
A344: 343 | B344: Dayna | C344: Quinn | D344: Miss | E344: F | F344: 60 | G344: Pembroke Square | H344: Penarth | I344: 40124 | J344: 47 | K344: A2
A345: 344 | B345: Madaline | C345: Hickey | D345: Mrs | E345: F | F345: 90 | G345: Dunsford Way | H345: Marlborough | I345: 40364 | J345: 100 | K345: D
A346: 345 | B346: Bernetta | C346: Moody | D346: Mrs | E346: F | F346: 30 | G346: Albion Yard | H346: Guernsey | I346: 39613 | J346: 90 | K346: C1
... A812: 811 | B812: Ingrid | C812: Flowers | D812: Miss | E812: F | F812: 60 | G812: Pilsdon Close | H812: Helmsdale | I812: 40509 | J812: 79 | K812: C2
A813: 812 | B813: Suzie | C813: Potts | D813: Miss | E813: F | F813: 90 | G813: Pekin Place | H813: Cromer | I813: 40441 | J813: 96
A814: 813 | B814: yoko | C814: Holden | D814: Mrs | E814: F | F814: 30 | G814: College Mews | H814: Attleborough | I814: 39641 | J814: 77 | K814: C2
A815: 814 | B815: Elvina | C815: Mcbride | D815: Mrs | E815: F | F815: 90 | G815: Mabley Street | H815: Newmarket | I815: 40480 | J815: 28 | K815: C1
A816: 815 | B816: Vernita | C816: Messer | D816: Mrs | E816: F | F816: 90 | G816: Chase Gardens | H816: Newcastle Emlyn | I816: 39666 | J816: 86 | K816: C2
A817: 816 | B817: Lea | C817: Weston | D817: Mrs | E817: F | F817: 90 | G817: Windus Road | H817: Sleaford | I817: 39473 | J817: 97 | K817: B
A818: 817 | B818: Mildred | C818: Nieves | D818: Miss | E818: F | F818: 60 | G818: Orleston Mews | H818: Leven | I818: 39955 | J818: 96 | K818: B
A819: 818 | B819: Shakira | C819: Major | D819: Miss | E819: F | F819: 90 | G819: Capitol Way | H819: Bedlington | I819: 39778 | J819: 29 | K819: C3
A820: 819 | B820: Harold | C820: Boykin | D820: Miss | E820: F | F820: 30 | G820: Stalham Street | H820: Merriott | I820: 39602 | J820: 75 | K820: A3
A821: 820 | B821: Velma | C821: Mcdonough | D821: Mrs | E821: F | F821: 30 | G821: The Sandhills | H821: Jedburgh | I821: 40045 | J821: 60 | K821: B
A822: 821 | B822: Lecia | C822: Ewing | D822: Miss | E822: F | F822: 90 | G822: Lydden Grove | H822: Cumbria | I822: 39666 | J822: 51 | K822: D
A823: 822 | B823: Adelia | C823: Kirk | D823: Miss | E823: F | F823: 30 | G823: Cornflower Terrace | H823: Snodland | I823: 39785 | J823: 93 | K823: A3
A824: 823 | B824: Rebeca | C824: Begay | D824: Mrs | E824: F | F824: 60 | G824: Highbury Crescent | H824: Stonehaven | I824: 40211 | J824: 26 | K824: C4
A825: 824 | B825: vanna | C825: Franklin | D825: Mrs | E825: F | F825: 30 | G825: Molesford Road | H825: Plockton | I825: 39831 | J825: 70 | K825: A1
... A1163: 1162 | B1163: Malik | C1163: Swanson | D1163: Mr | E1163: M | F1163: 60 | G1163: Horsmonden Road | H1163: Bognor Regis | I1163: 40074 | J1163: 26 | K1163: C1
A1164: 1163 | B1164: Filiberto | C1164: Wilson | D1164: Mr | E1164: M | F1164: 90 | G1164: Crown Dale | H1164: Hailsham | I1164: 40154 | J1164: 49
A1165: 1164 | B1165: Ward | C1165: Paulson | D1165: Mr | E1165: M | F1165: 30 | G1165: Golderton | H1165: Barry | I1165: 40384 | J1165: 93 | K1165: C2
A1166: 1165 | B1166: Eldon | C1166: Bass | D1166: Mr | E1166: M | F1166: 90 | G1166: Shrubbery Close | H1166: Wingate | I1166: 40293 | J1166: 15 | K1166: E
A1167: 1166 | B1167: Pat | C1167: Chu | D1167: Mr | E1167: M | F1167: 30 | G1167: India Road | H1167: Beaconsfield | I1167: 39708 | J1167: 15 | K1167: C3
A1168: 1167 | B1168: Waylon | C1168: Scott | D1168: Dr | E1168: M | F1168: 30 | G1168: Pakeman Street | H1168: Brighouse | I1168: 39794 | J1168: 11 | K1168: A1
A1169: 1168 | B1169: Noe | C1169: Suggs | D1169: Mr | E1169: M | F1169: 90 | G1169: Trollope Street | H1169: Dudley | I1169: 40453 | J1169: 98 | K1169: A3
A1170: 1169 | B1170: Edmundo | C1170: Fitzgerald | D1170: Mr | E1170: Mal e | F1170: 90 | G1170: Halcrow Street | H1170: Livingston | I1170: 39518 | J1170: 20 | K1170: C1
A1171: 1170 | B1171: Benjamin | C1171: Dodson | D1171: Mr | E1171: M | F1171: 90 | G1171: Anns Close | H1171: Macclesfield | I1171: 39480 | J1171: 73 | K1171: C1
A1172: 1171 | B1172: Burton | C1172: Lassiter | D1172: Mr | E1172: M | F1172: 60 | G1172: Telford Avenue | H1172: Ryde | I1172: 40321 | J1172: 26 | K1172: A3
A1173: 1172 | B1173: Vincenzo | C1173: 0 | D1173: Mr | E1173: M | F1173: 30 | G1173: Whitehall Yard | H1173: Perranporth | I1173: 40080 | J1173: 7 | K1173: A3
A1174: 1173 | B1174: Orval | C1174: Blount | D1174: Mr | E1174: M | F1174: 60 | G1174: Well Grove | H1174: Wilmslow | I1174: 39822 | J1174: 99 | K1174: C4
A1175: 1174 | B1175: Maynard | C1175: Mcmillan | D1175: Mr | E1175: m | F1175: 90 | G1175: Gunter Grove | H1175: Bembridge | I1175: 40102 | J1175: 57 | K1175: D
A1176: 1175 | B1176: Rodrigo | C1176: Stacy | D1176: Mr | E1176: M | F1176: 30 | G1176: Holbein Mews | H1176: East Grinstead | I1176: 40395 | J1176: 10 | K1176: A2
... A1209: 1208 | B1209: Glen | C1209: Jewell | D1209: Dr | E1209: M | F1209: 30 | G1209: Grange Lodge | H1209: Elland | I1209: 40176 | J1209: 15 | K1209: C2
A1210: 1209 | B1210: Devon | C1210: Cummings | D1210: Mr | E1210: M | G1210: Christopher Street | H1210: Lancashire | I1210: 39594 | J1210: 43 | K1210: C1
A1211: 1210 | B1211: Darrell | C1211: Rowell | D1211: Mr | E1211: M | F1211: 90 | G1211: Pardon Street | H1211: Banstead | I1211: 39466 | J1211: 69 | K1211: D
A1212: 1211 | B1212: Nathaniel | C1212: Laird | D1212: Mr | E1212: M | F1212: 60 | G1212: Geneva Court | H1212: Lymington | I1212: 40207 | J1212: 90 | K1212: B
A1213: 1212 | B1213: Hubert | C1213: Tanner | D1213: Mr | E1213: M | F1213: 30 | G1213: Gutteridge Court | H1213: Tadley | I1213: 40289 | J1213: 68 | K1213: D
A1214: 1213 | B1214: Isaiah | C1214: Hamm | D1214: Mr | E1214: M | F1214: 30 | G1214: Earles Cottages | H1214: Earlston | I1214: 40278 | J1214: 72 | K1214: C3
A1215: 1214 | B1215: Nolan | C1215: Akins | D1215: Mr | E1215: M | F1215: 90 | G1215: Royal Victoria | H1215: Wemyss Bay | I1215: 40295 | J1215: 25 | K1215: A3
...

Sheet Task 4.1 Counting Blank Cells
A1: ID | B1: First Name | C1: Last Name | D1: Title | E1: Gender | F1: Credit | G1: Street | H1: Town | I1: Order Date | J1: Quantity | K1: Product | L1: Blanks
A2: 1 | B2: Nanci | C2: Camp | D2: Mrs | E2: F | F2: 60 | G2: Rosmore Road | H2: Berkeley | I2: 39988 | J2: 13 | K2: A1 | L2: =COUNTBLANK(Portfolio43[[#This Row],[ID]:[Product]]) -> 0 | N2: STEPS
A3: 2 | B3: Erlinda | C3: Dorsey | D3: Mrs | E3: F | F3: 90 | G3: Roxwell Road | H3: Glossop | I3: 39770 | J3: 14 | K3: C3 | L3: =COUNTBLANK(Portfolio43[[#This Row],[ID]:[Product]]) -> 0 | N3: Used COUNTBLANK Function to Identify the total number of Blank Cells in the sheet
A4: 3 | B4: Albertha | C4: Devine | D4: Mrs | E4: F | F4: 60 | G4: Ashbury Place | H4: Immingham | I4: 39895 | J4: 23 | K4: E | L4: =COUNTBLANK(Portfolio43[[#This Row],[ID]:[Product]]) -> 0 | N4: Formula: | P4: COUNTBLANK(Portfolio43)
A5: 4 | B5: Nathalie | C5: Washington | D5: Miss | E5: F | F5: 60 | G5: Grafton Road | H5: Broadstone | I5: 39830 | J5: 79 | K5: E | L5: =COUNTBLANK(Portfolio43[[#This Row],[ID]:[Product]]) -> 0 | N5: Blank cells detected | P5: =COUNTBLANK(Portfolio43[]) -> 15
A6: 5 | B6: Shonta | C6: Hedrick | D6: Miss | E6: fem | F6: 60 | G6: Beechdale Road | H6: Port Talbot | I6: 39988 | J6: 44 | K6: C3 | L6: =COUNTBLANK(Portfolio43[[#This Row],[ID]:[Product]]) -> 0
A7: 6 | B7: Veronika | C7: Lundy | D7: Miss | E7: F | F7: 90 | G7: Katherine Gardens | H7: Ardgay | I7: 40316 | J7: 37 | K7: A3 | L7: =COUNTBLANK(Portfolio43[[#This Row],[ID]:[Product]]) -> 0 | N7: Added a new column named "Blanks" to identify the number of blank cells in each row by Using COUNTBLANK Function
A8: 7 | B8: Valeria | C8: Frost | D8: Mrs | E8: F | F8: 30 | G8: Ross Way | H8: Solihull | I8: 40202 | J8: 12 | K8: C2 | L8: =COUNTBLANK(Portfolio43[[#This Row],[ID]:[Product]]) -> 0
A9: 8 | B9: Randa | C9: Woods | D9: Mrs | E9: F | F9: 30 | G9: Artisans Dwellings | H9: Tring | I9: 40497 | J9: 55 | K9: C1 | L9: =COUNTBLANK(Portfolio43[[#This Row],[ID]:[Product]]) -> 0 | N9: Formula: | P9: COUNTBLANK(Portfolio43[@[ID]:[Product]])
A10: 9 | B10: Karole | C10: Navarro | D10: Mrs | E10: F | F10: 30 | G10: Rhoda Street | H10: St. Ives | I10: 39938 | J10: 10 | K10: C3 | L10: =COUNTBLANK(Portfolio43[[#This Row],[ID]:[Product]]) -> 0
A11: 10 | B11: Martin | C11: Anthony | D11: Miss | E11: F | F11: 90 | G11: Iceland Road | H11: Campbeltown | I11: 40466 | J11: 76 | K11: A2 | L11: =COUNTBLANK(Portfolio43[[#This Row],[ID]:[Product]]) -> 0 | N11: Used COUNTIF function to count the number of rows containing values greater than 0 in the Blanks column
A12: 11 | B12: Shanae | C12: Roland | D12: Mrs | E12: F | F12: 90 | G12: Samels Court | H12: Newbridge | I12: 40031 | J12: 28 | K12: C2 | L12: =COUNTBLANK(Portfolio43[[#This Row],[ID]:[Product]]) -> 0
A13: 12 | B13: Yen | C13: Culver | D13: Miss | E13: F | F13: 60 | G13: Garratt Green | H13: London | I13: 39965 | J13: 41 | K13: A2 | L13: =COUNTBLANK(Portfolio43[[#This Row],[ID]:[Product]]) -> 0 | N13: Formula: | P13: COUNTIF(L2:L2001,">0")
A14: 13 | B14: Monica | C14: Doran | D14: Miss | E14: F | F14: 90 | G14: High St | H14: Caldicot | I14: 39516 | J14: 48 | K14: B | L14: =COUNTBLANK(Portfolio43[[#This Row],[ID]:[Product]]) -> 0 | N14: Count | P14: =COUNTIF(Portfolio43[Blanks],">0") -> 14
A15: 14 | B15: Laureen | C15: Richards | D15: Prof | E15: F | F15: 90 | G15: Brackenfield Close | H15: Broseley | I15: 39665 | J15: 34 | K15: C4 | L15: =COUNTBLANK(Portfolio43[[#This Row],[ID]:[Product]]) -> 0
A16: 15 | B16: Meta | C16: Wright | D16: Mrs | E16: F | F16: 60 | G16: Bearstead Rise | H16: Y Felinheli | I16: 40337 | J16: 57 | K16: C4 | L16: =COUNTBLANK(Portfolio43[[#This Row],[ID]:[Product]]) -> 0 | N16: Using the Filter Option in the Blanks column we selected the values greater than 0 and deleted them
A17: 16 | B17: Bobbye | C17: Vasquez | D17: Mrs | E17: F | F17: 30 | G17: Baker Road | H17: Trowbridge | I17: 40532 | J17: 59 | K17: E | L17: =COUNTBLANK(Portfolio43[[#This Row],[ID]:[Product]]) -> 0
A18: 17 | B18: Emily | C18: Butler | D18: Miss | E18: F | F18: 30 | G18: Telford Close | H18: Isles Of Scilly | I18: 40271 | J18: 84 | K18: C1 | L18: =COUNTBLANK(Portfolio43[[#This Row],[ID]:[Product]]) -> 0
A19: 18 | B19: Iona | C19: Hutchinson | D19: Ms | E19: F | F19: 30 | G19: Queens Buildings | H19: Kilmacolm | I19: 40183 | J19: 39 | K19: C4 | L19: =COUNTBLANK(Portfolio43[[#This Row],[ID]:[Product]]) -> 0 | N19: Note: This Sheet is Password Protected, To unlock this sheet use "qwer" as password
A20: 19 | B20: Windy | C20: Cabrera | D20: Miss | E20: F | F20: 90 | G20: Havelock Cottages | H20: Bridgwater | I20: 40381 | J20: 54 | K20: A1 | L20: =COUNTBLANK(Portfolio43[[#This Row],[ID]:[Product]]) -> 0
A21: 20 | B21: Cherry | C21: Walsh | D21: Mrs | E21: F | F21: 90 | G21: Huntingdon Gardens | H21: Essex | I21: 40469 | J21: 33 | K21: C2 | L21: =COUNTBLANK(Portfolio43[[#This Row],[ID]:[Product]]) -> 0
A22: 21 | B22: Jaye | C22: FARLEY | D22: Mrs | E22: F | F22: 60 | G22: Embankment Gardens | H22: Badminton | I22: 39587 | J22: 84 | K22: C2 | L22: =COUNTBLANK(Portfolio43[[#This Row],[ID]:[Product]]) -> 0
A23: 22 | B23: Garnet | C23: Tipton | D23: Miss | E23: F | F23: 30 | G23: Burton Grove | H23: Halesowen | I23: 39993 | J23: 94 | K23: C1 | L23: =COUNTBLANK(Portfolio43[[#This Row],[ID]:[Product]]) -> 0
A24: 23 | B24: Coral | C24: Grace | D24: Miss | E24: F | F24: 90 | G24: Alliance Road | H24: Kyle | I24: 40470 | J24: 84 | K24: A1 | L24: =COUNTBLANK(Portfolio43[[#This Row],[ID]:[Product]]) -> 0
A25: 24 | B25: Kacy | C25: Ragland | D25: Miss | E25: F | F25: 90 | G25: Coningsby Cottages | H25: Cradley Heath | I25: 40052 | J25: 37 | K25: A3 | L25: =COUNTBLANK(Portfolio43[[#This Row],[ID]:[Product]]) -> 0
A26: 25 | B26: Riva | C26: Crosby | D26: Miss | E26: F | F26: 60 | G26: Burdett Place | H26: Frizington | I26: 40006 | J26: 3 | K26: C2 | L26: =COUNTBLANK(Portfolio43[[#This Row],[ID]:[Product]]) -> 0
A27: 26 | B27: Thi | C27: Stroud | D27: Mrs | E27: F | F27: 30 | G27: Biddenden Way | H27: Longfield | I27: 39893 | J27: 34 | K27: C1 | L27: =COUNTBLANK(Portfolio43[[#This Row],[ID]:[Product]]) -> 0
A28: 27 | B28: Ji | C28: Austin | D28: Mrs | E28: F | F28: 30 | G28: Selhurst Road | H28: Downham Market | I28: 40308 | J28: 78 | K28: A3 | L28: =COUNTBLANK(Portfolio43[[#This Row],[ID]:[Product]]) -> 0
A29: 28 | B29: Molly | C29: MARCUS | D29: Mrs | E29: F | F29: 90 | G29: Lyons Yard | H29: Lyme Regis | I29: 39916 | J29: 46 | K29: A3 | L29: =COUNTBLANK(Portfolio43[[#This Row],[ID]:[Product]]) -> 0
A30: 29 | B30: Alina | C30: Pryor | D30: Ms | E30: F | F30: 90 | G30: Edgar Road | H30: Cornwall | I30: 39906 | J30: 34 | K30: E | L30: =COUNTBLANK(Portfolio43[[#This Row],[ID]:[Product]]) -> 0
A31: 30 | B31: Jo | C31: Simons | D31: Mrs | E31: F | F31: 30 | G31: Roe Lane | H31: Pentre | I31: 39670 | J31: 64 | K31: E | L31: =COUNTBLANK(Portfolio43[[#This Row],[ID]:[Product]]) -> 0
... A95: 94 | B95: Waneta | C95: Klein | D95: Miss | E95: F | F95: 60 | G95: Kidd Place | H95: Strathdon | I95: 39833 | J95: 97 | K95: C3 | L95: =COUNTBLANK(Portfolio43[[#This Row],[ID]:[Product]]) -> 0
A96: 95 | B96: Jadwiga | C96: Contreras | E96: F | F96: 90 | G96: Little Lemon | H96: Llanrwst | I96: 40064 | J96: 24 | K96: E | L96: =COUNTBLANK(Portfolio43[[#This Row],[ID]:[Product]]) -> 1
A97: 96 | B97: Catherina | C97: Galvan | D97: Ms | E97: F | F97: 60 | G97: Little New | H97: Darwen | I97: 39927 | J97: 87 | K97: A2 | L97: =COUNTBLANK(Portfolio43[[#This Row],[ID]:[Product]]) -> 0
A98: 97 | B98: Leslie | C98: Hobson | D98: Mrs | E98: F | F98: 30 | G98: Templecombe Road | H98: Plockton | I98: 40500 | J98: 41 | K98: A2 | L98: =COUNTBLANK(Portfolio43[[#This Row],[ID]:[Product]]) -> 0
A99: 98 | B99: Jona | C99: Mcneill | D99: Miss | E99: F | F99: 90 | G99: Warner Road | H99: Coleford | I99: 40312 | J99: 68 | K99: E | L99: =COUNTBLANK(Portfolio43[[#This Row],[ID]:[Product]]) -> 0
A100: 99 | B100: Phylis | C100: Starks | D100: Mrs | E100: F | F100: 30 | G100: Du Burstow | H100: Surrey | I100: 40037 | J100: 47 | K100: B | L100: =COUNTBLANK(Portfolio43[[#This Row],[ID]:[Product]]) -> 0
A101: 100 | B101: Chasidy | C101: Pittman | D101: Miss | E101: F | F101: 90 | G101: Vine Cottages | H101: Tewkesbury | I101: 40107 | J101: 51 | K101: C1 | L101: =COUNTBLANK(Portfolio43[[#This Row],[ID]:[Product]]) -> 0
A102: 101 | B102: Rina | C102: Hayes | D102: Mrs | E102: F | F102: 60 | G102: Jamaica Level | H102: Buxton | I102: 40000 | J102: 97 | K102: B | L102: =COUNTBLANK(Portfolio43[[#This Row],[ID]:[Product]]) -> 0
A103: 102 | B103: Piedad | C103: Mcmullen | D103: Miss | E103: F | F103: 90 | G103: College Yard | H103: Colchester | I103: 40526 | J103: 70 | K103: C2 | L103: =COUNTBLANK(Portfolio43[[#This Row],[ID]:[Product]]) -> 0
A104: 103 | B104: Wanda | C104: Eubanks | D104: Mrs | E104: F | F104: 90 | G104: Woodington Close | H104: Bushmills | I104: 39760 | J104: 83 | K104: E | L104: =COUNTBLANK(Portfolio43[[#This Row],[ID]:[Product]]) -> 0
A105: 104 | B105: Taunya | C105: Medeiros | D105: Miss | E105: F | F105: 60 | G105: Westmoreland Mews | H105: Ross-Shire | I105: 39862 | J105: 63 | K105: A2 | L105: =COUNTBLANK(Portfolio43[[#This Row],[ID]:[Product]]) -> 0
A106: 105 | B106: Carla | C106: Grover | D106: Mrs | E106: F | F106: 60 | G106: Deepdene Close | H106: Wotton-Under-Edge | I106: 39523 | J106: 67 | K106: C2 | L106: =COUNTBLANK(Portfolio43[[#This Row],[ID]:[Product]]) -> 0
A107: 106 | B107: Moon | C107: Cervantes | D107: Miss | E107: F | F107: 90 | G107: Broadbridge Close | H107: Sedbergh | I107: 39698 | J107: 65 | K107: A2 | L107: =COUNTBLANK(Portfolio43[[#This Row],[ID]:[Product]]) -> 0
A108: 107 | B108: Christin | C108: Wolfe | D108: Mrs | E108: F | F108: 30 | G108: Christchurch Mews | H108: Wells-Next-The-Sea | I108: 40106 | J108: 45 | K108: E | L108: =COUNTBLANK(Portfolio43[[#This Row],[ID]:[Product]]) -> 0
... A212: 211 | B212: Rebbeca | C212: Middleton | D212: Miss | E212: F | F212: 30 | G212: Harberson Road | H212: Attleborough | I212: 40078 | J212: 63 | K212: A1 | L212: =COUNTBLANK(Portfolio43[[#This Row],[ID]:[Product]]) -> 0
A213: 212 | B213: Paula | C213: Duke | D213: Mrs | E213: F | G213: Colonial House | H213: Ammanford | I213: 39786 | J213: 15 | K213: A3 | L213: =COUNTBLANK(Portfolio43[[#This Row],[ID]:[Product]]) -> 1
A214: 213 | B214: Kristie | C214: Santos | D214: Miss | E214: F | F214: 90 | G214: Pembridge Crescent | H214: Portsmouth | I214: 39641 | J214: 82 | K214: A3 | L214: =COUNTBLANK(Portfolio43[[#This Row],[ID]:[Product]]) -> 0
A215: 214 | B215: Bernarda | C215: Knutson | D215: Miss | E215: F | F215: 30 | G215: Searles Close | H215: Llanfyrnach | I215: 40340 | J215: 81 | K215: C1 | L215: =COUNTBLANK(Portfolio43[[#This Row],[ID]:[Product]]) -> 0
A216: 215 | B216: Mandy | C216: York | D216: Mrs | E216: F | F216: 60 | G216: Beatrice Place | H216: Kinlochleven | I216: 40232 | J216: 50 | K216: A1 | L216: =COUNTBLANK(Portfolio43[[#This Row],[ID]:[Product]]) -> 0
A217: 216 | B217: Francina | C217: Corley | D217: Miss | E217: F | F217: 90 | G217: Stewart Road | H217: Ventnor | J217: 55 | K217: C2 | L217: =COUNTBLANK(Portfolio43[[#This Row],[ID]:[Product]]) -> 1
A218: 217 | B218: Evan | C218: Holmes | D218: Mrs | E218: F | F218: 60 | G218: Stanthorpe Close | H218: Helensburgh | I218: 40439 | J218: 72 | K218: C4 | L218: =COUNTBLANK(Portfolio43[[#This Row],[ID]:[Product]]) -> 0
A219: 218 | B219: Julieann | C219: Numbers | D219: Miss | E219: F | F219: 60 | G219: Portman Gardens | H219: South Yorkshire | I219: 39516 | J219: 93 | K219: E | L219: =COUNTBLANK(Portfolio43[[#This Row],[ID]:[Product]]) -> 0
A220: 219 | B220: Francesca | C220: Neal | D220: Miss | E220: F | F220: 90 | G220: Friars Close | H220: Hawes | I220: 40146 | J220: 98 | K220: B | L220: =COUNTBLANK(Portfolio43[[#This Row],[ID]:[Product]]) -> 0
A221: 220 | B221: Priscila | C221: Sewell | D221: Ms | E221: F | F221: 30 | G221: Popes Lane | H221: Carnoustie | I221: 39909 | J221: 92 | K221: C2 | L221: =COUNTBLANK(Portfolio43[[#This Row],[ID]:[Product]]) -> 0
A222: 221 | B222: Shakira | C222: Krueger | D222: Mrs | E222: F | F222: 90 | G222: Mutton Place | H222: Colne | I222: 39493 | J222: 10 | K222: C4 | L222: =COUNTBLANK(Portfolio43[[#This Row],[ID]:[Product]]) -> 0
A223: 222 | B223: Cornelia | C223: Moreland | D223: Miss | E223: F | F223: 60 | G223: Thorndean Street | H223: Studley | I223: 40291 | J223: 27 | K223: A2 | L223: =COUNTBLANK(Portfolio43[[#This Row],[ID]:[Product]]) -> 0
A224: 223 | B224: Lyndsey | C224: Neely | D224: Mrs | E224: F | F224: 30 | G224: Fardon Row | H224: Morecambe | I224: 40295 | J224: 28 | K224: D | L224: =COUNTBLANK(Portfolio43[[#This Row],[ID]:[Product]]) -> 0
A225: 224 | B225: Nettie | C225: Smiley | D225: Mrs | E225: F | F225: 30 | G225: Bedale Street | H225: Montgomery | I225: 40063 | J225: 30 | K225: C2 | L225: =COUNTBLANK(Portfolio43[[#This Row],[ID]:[Product]]) -> 0
A226: 225 | B226: Ebony | C226: Simms | D226: Mrs | E226: F | F226: 30 | G226: Sussex Cottage | H226: Trowbridge | I226: 40064 | J226: 53 | K226: A1 | L226: =COUNTBLANK(Portfolio43[[#This Row],[ID]:[Product]]) -> 0
A227: 226 | B227: Lilli | C227: Contreras | D227: Miss | E227: F | F227: 60 | G227: Claverley Grove | H227: Immingham | I227: 39523 | J227: 89 | K227: A2 | L227: =COUNTBLANK(Portfolio43[[#This Row],[ID]:[Product]]) -> 0
A228: 227 | B228: Grisel | C228: Comer | D228: Mrs | E228: F | F228: 90 | G228: Talfourd Place | H228: North Humberside | I228: 39461 | J228: 22 | K228: C2 | L228: =COUNTBLANK(Portfolio43[[#This Row],[ID]:[Product]]) -> 0
A229: 228 | B229: Lorinda | C229: Pate | D229: Miss | E229: F | F229: 90 | G229: Stock Street | H229: Bala | I229: 39775 | J229: 71 | K229: E | L229: =COUNTBLANK(Portfolio43[[#This Row],[ID]:[Product]]) -> 0
... A333: 332 | B333: Remedios | C333: Bolton | D333: Mrs | E333: F | F333: 90 | G333: Lion Yard | H333: Monmouth | I333: 39782 | J333: 65 | K333: A3 | L333: =COUNTBLANK(Portfolio43[[#This Row],[ID]:[Product]]) -> 0
A334: 333 | B334: Lilian | C334: Schneider | D334: Miss | E334: F | F334: 60 | G334: Ponsonby Street | H334: Hastings | I334: 40286 | J334: 42 | L334: =COUNTBLANK(Portfolio43[[#This Row],[ID]:[Product]]) -> 1
A335: 334 | B335: Karma | C335: Stahl | D335: Mrs | E335: F | F335: 30 | G335: Broomhouse Road | H335: Lynmouth | I335: 40340 | J335: 36 | K335: A2 | L335: =COUNTBLANK(Portfolio43[[#This Row],[ID]:[Product]]) -> 0
A336: 335 | B336: Irmgard | C336: Askew | D336: Mrs | E336: F | F336: 30 | G336: Dudley Villas | H336: Buckley | I336: 39785 | J336: 27 | K336: A2 | L336: =COUNTBLANK(Portfolio43[[#This Row],[ID]:[Product]]) -> 0
A337: 336 | B337: Yan | C337: Alford | D337: Mrs | E337: F | F337: 60 | G337: Thurlestone Avenue | H337: Eastbourne | I337: 39700 | J337: 86 | K337: A2 | L337: =COUNTBLANK(Portfolio43[[#This Row],[ID]:[Product]]) -> 0
A338: 337 | B338: Felecia | C338: Rose | D338: Mrs | E338: F | F338: 60 | G338: Copleston Mews | H338: Broxbourne | I338: 40228 | J338: 26 | K338: A3 | L338: =COUNTBLANK(Portfolio43[[#This Row],[ID]:[Product]]) -> 0
A339: 338 | B339: Loreen | C339: Boykin | D339: Mrs | E339: F | F339: 60 | G339: Northburgh Street | H339: Sheerness | I339: 40445 | J339: 78 | K339: A3 | L339: =COUNTBLANK(Portfolio43[[#This Row],[ID]:[Product]]) -> 0
A340: 339 | B340: Ranee | C340: Herndon | D340: Miss | E340: F | F340: 60 | G340: Brunswick Industrial | H340: Cullompton | I340: 39697 | J340: 84 | K340: D | L340: =COUNTBLANK(Portfolio43[[#This Row],[ID]:[Product]]) -> 0
A341: 340 | B341: Sena | C341: Bass | D341: Miss | E341: F | F341: 60 | G341: Lansdowne Walk | H341: South Yorkshire | I341: 40076 | J341: 65 | K341: D | L341: =COUNTBLANK(Portfolio43[[#This Row],[ID]:[Product]]) -> 0
A342: 341 | B342: Annmarie | C342: Hearn | D342: Dr | E342: F | F342: 90 | G342: Brent Park | H342: Penrhyndeudraeth | I342: 40161 | J342: 82 | K342: E | L342: =COUNTBLANK(Portfolio43[[#This Row],[ID]:[Product]]) -> 0
A343: 342 | B343: Eileen | C343: Walden | D343: Miss | E343: F | F343: 90 | G343: Newmarket Terrace | H343: Brandon | I343: 39971 | J343: 37 | K343: A1 | L343: =COUNTBLANK(Portfolio43[[#This Row],[ID]:[Product]]) -> 0
A344: 343 | B344: Dayna | C344: Quinn | D344: Miss | E344: F | F344: 60 | G344: Pembroke Square | H344: Penarth | I344: 40124 | J344: 47 | K344: A2 | L344: =COUNTBLANK(Portfolio43[[#This Row],[ID]:[Product]]) -> 0
A345: 344 | B345: Madaline | C345: Hickey | D345: Mrs | E345: F | F345: 90 | G345: Dunsford Way | H345: Marlborough | I345: 40364 | J345: 100 | K345: D | L345: =COUNTBLANK(Portfolio43[[#This Row],[ID]:[Product]]) -> 0
A346: 345 | B346: Bernetta | C346: Moody | D346: Mrs | E346: F | F346: 30 | G346: Albion Yard | H346: Guernsey | I346: 39613 | J346: 90 | K346: C1 | L346: =COUNTBLANK(Portfolio43[[#This Row],[ID]:[Product]]) -> 0
... A812: 811 | B812: Ingrid | C812: Flowers | D812: Miss | E812: F | F812: 60 | G812: Pilsdon Close | H812: Helmsdale | I812: 40509 | J812: 79 | K812: C2 | L812: =COUNTBLANK(Portfolio43[[#This Row],[ID]:[Product]]) -> 0
A813: 812 | B813: Suzie | C813: Potts | D813: Miss | E813: F | F813: 90 | G813: Pekin Place | H813: Cromer | I813: 40441 | J813: 96 | L813: =COUNTBLANK(Portfolio43[[#This Row],[ID]:[Product]]) -> 1
A814: 813 | B814: yoko | C814: Holden | D814: Mrs | E814: F | F814: 30 | G814: College Mews | H814: Attleborough | I814: 39641 | J814: 77 | K814: C2 | L814: =COUNTBLANK(Portfolio43[[#This Row],[ID]:[Product]]) -> 0
A815: 814 | B815: Elvina | C815: Mcbride | D815: Mrs | E815: F | F815: 90 | G815: Mabley Street | H815: Newmarket | I815: 40480 | J815: 28 | K815: C1 | L815: =COUNTBLANK(Portfolio43[[#This Row],[ID]:[Product]]) -> 0
A816: 815 | B816: Vernita | C816: Messer | D816: Mrs | E816: F | F816: 90 | G816: Chase Gardens | H816: Newcastle Emlyn | I816: 39666 | J816: 86 | K816: C2 | L816: =COUNTBLANK(Portfolio43[[#This Row],[ID]:[Product]]) -> 0
A817: 816 | B817: Lea | C817: Weston | D817: Mrs | E817: F | F817: 90 | G817: Windus Road | H817: Sleaford | I817: 39473 | J817: 97 | K817: B | L817: =COUNTBLANK(Portfolio43[[#This Row],[ID]:[Product]]) -> 0
A818: 817 | B818: Mildred | C818: Nieves | D818: Miss | E818: F | F818: 60 | G818: Orleston Mews | H818: Leven | I818: 39955 | J818: 96 | K818: B | L818: =COUNTBLANK(Portfolio43[[#This Row],[ID]:[Product]]) -> 0
A819: 818 | B819: Shakira | C819: Major | D819: Miss | E819: F | F819: 90 | G819: Capitol Way | H819: Bedlington | I819: 39778 | J819: 29 | K819: C3 | L819: =COUNTBLANK(Portfolio43[[#This Row],[ID]:[Product]]) -> 0
A820: 819 | B820: Harold | C820: Boykin | D820: Miss | E820: F | F820: 30 | G820: Stalham Street | H820: Merriott | I820: 39602 | J820: 75 | K820: A3 | L820: =COUNTBLANK(Portfolio43[[#This Row],[ID]:[Product]]) -> 0
A821: 820 | B821: Velma | C821: Mcdonough | D821: Mrs | E821: F | F821: 30 | G821: The Sandhills | H821: Jedburgh | I821: 40045 | J821: 60 | K821: B | L821: =COUNTBLANK(Portfolio43[[#This Row],[ID]:[Product]]) -> 0
A822: 821 | B822: Lecia | C822: Ewing | D822: Miss | E822: F | F822: 90 | G822: Lydden Grove | H822: Cumbria | I822: 39666 | J822: 51 | K822: D | L822: =COUNTBLANK(Portfolio43[[#This Row],[ID]:[Product]]) -> 0
A823: 822 | B823: Adelia | C823: Kirk | D823: Miss | E823: F | F823: 30 | G823: Cornflower Terrace | H823: Snodland | I823: 39785 | J823: 93 | K823: A3 | L823: =COUNTBLANK(Portfolio43[[#This Row],[ID]:[Product]]) -> 0
A824: 823 | B824: Rebeca | C824: Begay | D824: Mrs | E824: F | F824: 60 | G824: Highbury Crescent | H824: Stonehaven | I824: 40211 | J824: 26 | K824: C4 | L824: =COUNTBLANK(Portfolio43[[#This Row],[ID]:[Product]]) -> 0
A825: 824 | B825: vanna | C825: Franklin | D825: Mrs | E825: F | F825: 30 | G825: Molesford Road | H825: Plockton | I825: 39831 | J825: 70 | K825: A1 | L825: =COUNTBLANK(Portfolio43[[#This Row],[ID]:[Product]]) -> 0
... A1163: 1162 | B1163: Malik | C1163: Swanson | D1163: Mr | E1163: M | F1163: 60 | G1163: Horsmonden Road | H1163: Bognor Regis | I1163: 40074 | J1163: 26 | K1163: C1 | L1163: =COUNTBLANK(Portfolio43[[#This Row],[ID]:[Product]]) -> 0
A1164: 1163 | B1164: Filiberto | C1164: Wilson | D1164: Mr | E1164: M | F1164: 90 | G1164: Crown Dale | H1164: Hailsham | I1164: 40154 | J1164: 49 | L1164: =COUNTBLANK(Portfolio43[[#This Row],[ID]:[Product]]) -> 1
A1165: 1164 | B1165: Ward | C1165: Paulson | D1165: Mr | E1165: M | F1165: 30 | G1165: Golderton | H1165: Barry | I1165: 40384 | J1165: 93 | K1165: C2 | L1165: =COUNTBLANK(Portfolio43[[#This Row],[ID]:[Product]]) -> 0
A1166: 1165 | B1166: Eldon | C1166: Bass | D1166: Mr | E1166: M | F1166: 90 | G1166: Shrubbery Close | H1166: Wingate | I1166: 40293 | J1166: 15 | K1166: E | L1166: =COUNTBLANK(Portfolio43[[#This Row],[ID]:[Product]]) -> 0
A1167: 1166 | B1167: Pat | C1167: Chu | D1167: Mr | E1167: M | F1167: 30 | G1167: India Road | H1167: Beaconsfield | I1167: 39708 | J1167: 15 | K1167: C3 | L1167: =COUNTBLANK(Portfolio43[[#This Row],[ID]:[Product]]) -> 0
A1168: 1167 | B1168: Waylon | C1168: Scott | D1168: Dr | E1168: M | F1168: 30 | G1168: Pakeman Street | H1168: Brighouse | I1168: 39794 | J1168: 11 | K1168: A1 | L1168: =COUNTBLANK(Portfolio43[[#This Row],[ID]:[Product]]) -> 0
A1169: 1168 | B1169: Noe | C1169: Suggs | D1169: Mr | E1169: M | F1169: 90 | G1169: Trollope Street | H1169: Dudley | I1169: 40453 | J1169: 98 | K1169: A3 | L1169: =COUNTBLANK(Portfolio43[[#This Row],[ID]:[Product]]) -> 0
A1170: 1169 | B1170: Edmundo | C1170: Fitzgerald | D1170: Mr | E1170: Mal e | F1170: 90 | G1170: Halcrow Street | H1170: Livingston | I1170: 39518 | J1170: 20 | K1170: C1 | L1170: =COUNTBLANK(Portfolio43[[#This Row],[ID]:[Product]]) -> 0
A1171: 1170 | B1171: Benjamin | C1171: Dodson | D1171: Mr | E1171: M | F1171: 90 | G1171: Anns Close | H1171: Macclesfield | I1171: 39480 | J1171: 73 | K1171: C1 | L1171: =COUNTBLANK(Portfolio43[[#This Row],[ID]:[Product]]) -> 0
...

Sheet Task 4.1 Deleting Blank Cells
A1: ID | B1: First Name | C1: Last Name | D1: Title | E1: Gender | F1: Credit | G1: Street | H1: Town | I1: Order Date | J1: Quantity | K1: Product | L1: Blanks
A2: 1 | B2: Nanci | C2: Camp | D2: Mrs | E2: F | F2: 60 | G2: Rosmore Road | H2: Berkeley | I2: 39988 | J2: 13 | K2: A1 | L2: =COUNTBLANK(Portfolio434[[#This Row],[ID]:[Product]]) -> 0 | N2: STEPS
A3: 2 | B3: Erlinda | C3: Dorsey | D3: Mrs | E3: F | F3: 90 | G3: Roxwell Road | H3: Glossop | I3: 39770 | J3: 14 | K3: C3 | L3: =COUNTBLANK(Portfolio434[[#This Row],[ID]:[Product]]) -> 0 | N3: The Below values were observed after deleting the blank cells in the Table
A4: 3 | B4: Albertha | C4: Devine | D4: Mrs | E4: F | F4: 60 | G4: Ashbury Place | H4: Immingham | I4: 39895 | J4: 23 | K4: E | L4: =COUNTBLANK(Portfolio434[[#This Row],[ID]:[Product]]) -> 0 | N4: Used COUNTBLANK Function to Identify the total number of Blank Cells in the sheet
A5: 4 | B5: Nathalie | C5: Washington | D5: Miss | E5: F | F5: 60 | G5: Grafton Road | H5: Broadstone | I5: 39830 | J5: 79 | K5: E | L5: =COUNTBLANK(Portfolio434[[#This Row],[ID]:[Product]]) -> 0 | N5: Formula: | P5: COUNTBLANK(Portfolio43)
A6: 5 | B6: Shonta | C6: Hedrick | D6: Miss | E6: fem | F6: 60 | G6: Beechdale Road | H6: Port Talbot | I6: 39988 | J6: 44 | K6: C3 | L6: =COUNTBLANK(Portfolio434[[#This Row],[ID]:[Product]]) -> 0 | N6: Blank cells detected | P6: =COUNTBLANK(Portfolio434[]) -> 0
A7: 6 | B7: Veronika | C7: Lundy | D7: Miss | E7: F | F7: 90 | G7: Katherine Gardens | H7: Ardgay | I7: 40316 | J7: 37 | K7: A3 | L7: =COUNTBLANK(Portfolio434[[#This Row],[ID]:[Product]]) -> 0
A8: 7 | B8: Valeria | C8: Frost | D8: Mrs | E8: F | F8: 30 | G8: Ross Way | H8: Solihull | I8: 40202 | J8: 12 | K8: C2 | L8: =COUNTBLANK(Portfolio434[[#This Row],[ID]:[Product]]) -> 0 | N8: Added a new column named "Blanks" to identify the number of blank cells in each row by Using COUNTBLANK Function
A9: 8 | B9: Randa | C9: Woods | D9: Mrs | E9: F | F9: 30 | G9: Artisans Dwellings | H9: Tring | I9: 40497 | J9: 55 | K9: C1 | L9: =COUNTBLANK(Portfolio434[[#This Row],[ID]:[Product]]) -> 0
A10: 9 | B10: Karole | C10: Navarro | D10: Mrs | E10: F | F10: 30 | G10: Rhoda Street | H10: St. Ives | I10: 39938 | J10: 10 | K10: C3 | L10: =COUNTBLANK(Portfolio434[[#This Row],[ID]:[Product]]) -> 0 | N10: Formula: | P10: COUNTBLANK(Portfolio43[@[ID]:[Product]])
A11: 10 | B11: Martin | C11: Anthony | D11: Miss | E11: F | F11: 90 | G11: Iceland Road | H11: Campbeltown | I11: 40466 | J11: 76 | K11: A2 | L11: =COUNTBLANK(Portfolio434[[#This Row],[ID]:[Product]]) -> 0
A12: 11 | B12: Shanae | C12: Roland | D12: Mrs | E12: F | F12: 90 | G12: Samels Court | H12: Newbridge | I12: 40031 | J12: 28 | K12: C2 | L12: =COUNTBLANK(Portfolio434[[#This Row],[ID]:[Product]]) -> 0 | N12: Used COUNTIF function to count the number of rows containing values greater than 0 in the Blanks column
A13: 12 | B13: Yen | C13: Culver | D13: Miss | E13: F | F13: 60 | G13: Garratt Green | H13: London | I13: 39965 | J13: 41 | K13: A2 | L13: =COUNTBLANK(Portfolio434[[#This Row],[ID]:[Product]]) -> 0
A14: 13 | B14: Monica | C14: Doran | D14: Miss | E14: F | F14: 90 | G14: High St | H14: Caldicot | I14: 39516 | J14: 48 | K14: B | L14: =COUNTBLANK(Portfolio434[[#This Row],[ID]:[Product]]) -> 0 | N14: Formula: | P14: COUNTIF(L2:L2001,">0")
A15: 14 | B15: Laureen | C15: Richards | D15: Prof | E15: F | F15: 90 | G15: Brackenfield Close | H15: Broseley | I15: 39665 | J15: 34 | K15: C4 | L15: =COUNTBLANK(Portfolio434[[#This Row],[ID]:[Product]]) -> 0 | N15: Count | P15: =COUNTIF(Portfolio434[Blanks],">0") -> 0
A16: 15 | B16: Meta | C16: Wright | D16: Mrs | E16: F | F16: 60 | G16: Bearstead Rise | H16: Y Felinheli | I16: 40337 | J16: 57 | K16: C4 | L16: =COUNTBLANK(Portfolio434[[#This Row],[ID]:[Product]]) -> 0
A17: 16 | B17: Bobbye | C17: Vasquez | D17: Mrs | E17: F | F17: 30 | G17: Baker Road | H17: Trowbridge | I17: 40532 | J17: 59 | K17: E | L17: =COUNTBLANK(Portfolio434[[#This Row],[ID]:[Product]]) -> 0 | N17: The remaining values were identifyed using the SUBTOTAL function
A18: 17 | B18: Emily | C18: Butler | D18: Miss | E18: F | F18: 30 | G18: Telford Close | H18: Isles Of Scilly | I18: 40271 | J18: 84 | K18: C1 | L18: =COUNTBLANK(Portfolio434[[#This Row],[ID]:[Product]]) -> 0 | N18: Formula : =SUBTOTAL(3,A2:A1987)
A19: 18 | B19: Iona | C19: Hutchinson | D19: Ms | E19: F | F19: 30 | G19: Queens Buildings | H19: Kilmacolm | I19: 40183 | J19: 39 | K19: C4 | L19: =COUNTBLANK(Portfolio434[[#This Row],[ID]:[Product]]) -> 0 | N19: Blank rows deleted | P19: =2000-P20 -> 14
A20: 19 | B20: Windy | C20: Cabrera | D20: Miss | E20: F | F20: 90 | G20: Havelock Cottages | H20: Bridgwater | I20: 40381 | J20: 54 | K20: A1 | L20: =COUNTBLANK(Portfolio434[[#This Row],[ID]:[Product]]) -> 0 | N20: Values | P20: =SUBTOTAL(3,A2:A1987) -> 1986
A21: 20 | B21: Cherry | C21: Walsh | D21: Mrs | E21: F | F21: 90 | G21: Huntingdon Gardens | H21: Essex | I21: 40469 | J21: 33 | K21: C2 | L21: =COUNTBLANK(Portfolio434[[#This Row],[ID]:[Product]]) -> 0
A22: 21 | B22: Jaye | C22: FARLEY | D22: Mrs | E22: F | F22: 60 | G22: Embankment Gardens | H22: Badminton | I22: 39587 | J22: 84 | K22: C2 | L22: =COUNTBLANK(Portfolio434[[#This Row],[ID]:[Product]]) -> 0 | N22: Note: This Sheet is Password Protected, To unlock this sheet use "qwer" as password
A23: 22 | B23: Garnet | C23: Tipton | D23: Miss | E23: F | F23: 30 | G23: Burton Grove | H23: Halesowen | I23: 39993 | J23: 94 | K23: C1 | L23: =COUNTBLANK(Portfolio434[[#This Row],[ID]:[Product]]) -> 0
A24: 23 | B24: Coral | C24: Grace | D24: Miss | E24: F | F24: 90 | G24: Alliance Road | H24: Kyle | I24: 40470 | J24: 84 | K24: A1 | L24: =COUNTBLANK(Portfolio434[[#This Row],[ID]:[Product]]) -> 0
A25: 24 | B25: Kacy | C25: Ragland | D25: Miss | E25: F | F25: 90 | G25: Coningsby Cottages | H25: Cradley Heath | I25: 40052 | J25: 37 | K25: A3 | L25: =COUNTBLANK(Portfolio434[[#This Row],[ID]:[Product]]) -> 0
A26: 25 | B26: Riva | C26: Crosby | D26: Miss | E26: F | F26: 60 | G26: Burdett Place | H26: Frizington | I26: 40006 | J26: 3 | K26: C2 | L26: =COUNTBLANK(Portfolio434[[#This Row],[ID]:[Product]]) -> 0
A27: 26 | B27: Thi | C27: Stroud | D27: Mrs | E27: F | F27: 30 | G27: Biddenden Way | H27: Longfield | I27: 39893 | J27: 34 | K27: C1 | L27: =COUNTBLANK(Portfolio434[[#This Row],[ID]:[Product]]) -> 0
A28: 27 | B28: Ji | C28: Austin | D28: Mrs | E28: F | F28: 30 | G28: Selhurst Road | H28: Downham Market | I28: 40308 | J28: 78 | K28: A3 | L28: =COUNTBLANK(Portfolio434[[#This Row],[ID]:[Product]]) -> 0
A29: 28 | B29: Molly | C29: MARCUS | D29: Mrs | E29: F | F29: 90 | G29: Lyons Yard | H29: Lyme Regis | I29: 39916 | J29: 46 | K29: A3 | L29: =COUNTBLANK(Portfolio434[[#This Row],[ID]:[Product]]) -> 0
A30: 29 | B30: Alina | C30: Pryor | D30: Ms | E30: F | F30: 90 | G30: Edgar Road | H30: Cornwall | I30: 39906 | J30: 34 | K30: E | L30: =COUNTBLANK(Portfolio434[[#This Row],[ID]:[Product]]) -> 0
A31: 30 | B31: Jo | C31: Simons | D31: Mrs | E31: F | F31: 30 | G31: Roe Lane | H31: Pentre | I31: 39670 | J31: 64 | K31: E | L31: =COUNTBLANK(Portfolio434[[#This Row],[ID]:[Product]]) -> 0
A32: 31 | B32: Lacy | C32: Emerson | D32: Miss | E32: F | F32: 90 | G32: Beaufort Wharf | H32: Cirencester | I32: 39552 | J32: 80 | K32: D | L32: =COUNTBLANK(Portfolio434[[#This Row],[ID]:[Product]]) -> 0
A33: 32 | B33: Janice | C33: Oneal | D33: Miss | E33: F | F33: 60 | G33: Anns Close | H33: Ellesmere | I33: 40508 | J33: 88 | K33: B | L33: =COUNTBLANK(Portfolio434[[#This Row],[ID]:[Product]]) -> 0
A34: 33 | B34: Donella | C34: Fenton | D34: Miss | E34: F | F34: 90 | G34: Sladedale Road | H34: Newnham | I34: 39534 | J34: 60 | K34: E | L34: =COUNTBLANK(Portfolio434[[#This Row],[ID]:[Product]]) -> 0
... A1987: 2000 | B1987: Gaston | C1987: Guy | D1987: Mr | E1987: M | F1987: 60 | G1987: Wansbeck Road | H1987: Ledbury | I1987: 40301 | J1987: 58 | K1987: D | L1987: =COUNTBLANK(Portfolio434[[#This Row],[ID]:[Product]]) -> 0

Sheet Task 4.2
A1: ID | B1: First Name | C1: Last Name | D1: Title | E1: Gender | F1: Credit | G1: Street | H1: Town | I1: Order Date | J1: Quantity | K1: Product | M1: Last Name Correction | N1: Records Affected | O1: Gender Correction | P1: Records Affected2 | Q1: Initials
A2: 1 | B2: Nanci | C2: Camp | D2: Mrs | E2: F | F2: 60 | G2: Rosmore Road | H2: Berkeley | I2: 39988 | J2: 13 | K2: A1 | M2: =PROPER(Portfolio4346[[#This Row],[Last Name]]) -> Camp | N2: =IF(EXACT(C2,M2)=TRUE, "-", "Corrected to Title Case") -> - | O2: =IF(LEFT(E2,1)="f","F","M") -> F | P2: =IF(EXACT(E2,O2)=TRUE,"-","Corrected Errors") -> - | Q2: =UPPER(LEFT(B2,1)) -> N | S2: STEPS
A3: 2 | B3: Erlinda | C3: Dorsey | D3: Mrs | E3: F | F3: 90 | G3: Roxwell Road | H3: Glossop | I3: 39770 | J3: 14 | K3: C3 | M3: =PROPER(Portfolio4346[[#This Row],[Last Name]]) -> Dorsey | N3: =IF(EXACT(C3,M3)=TRUE, "-", "Corrected to Title Case") -> - | O3: =IF(LEFT(E3,1)="f","F","M") -> F | P3: =IF(EXACT(E3,O3)=TRUE,"-","Corrected Errors") -> - | Q3: =UPPER(LEFT(B3,1)) -> E | S3: 1. Created a new column named "Last Name Correction"
A4: 3 | B4: Albertha | C4: Devine | D4: Mrs | E4: F | F4: 60 | G4: Ashbury Place | H4: Immingham | I4: 39895 | J4: 23 | K4: E | M4: =PROPER(Portfolio4346[[#This Row],[Last Name]]) -> Devine | N4: =IF(EXACT(C4,M4)=TRUE, "-", "Corrected to Title Case") -> - | O4: =IF(LEFT(E4,1)="f","F","M") -> F | P4: =IF(EXACT(E4,O4)=TRUE,"-","Corrected Errors") -> - | Q4: =UPPER(LEFT(B4,1)) -> A | S4: Used the PROPER function to change the Last Name from Upper Case to Title Case
A5: 4 | B5: Nathalie | C5: Washington | D5: Miss | E5: F | F5: 60 | G5: Grafton Road | H5: Broadstone | I5: 39830 | J5: 79 | K5: E | M5: =PROPER(Portfolio4346[[#This Row],[Last Name]]) -> Washington | N5: =IF(EXACT(C5,M5)=TRUE, "-", "Corrected to Title Case") -> - | O5: =IF(LEFT(E5,1)="f","F","M") -> F | P5: =IF(EXACT(E5,O5)=TRUE,"-","Corrected Errors") -> - | Q5: =UPPER(LEFT(B5,1)) -> N | S5: Formula: =PROPER(Portfolio4346[@[Last Name]])
A6: 5 | B6: Shonta | C6: Hedrick | D6: Miss | E6: fem | F6: 60 | G6: Beechdale Road | H6: Port Talbot | I6: 39988 | J6: 44 | K6: C3 | M6: =PROPER(Portfolio4346[[#This Row],[Last Name]]) -> Hedrick | N6: =IF(EXACT(C6,M6)=TRUE, "-", "Corrected to Title Case") -> - | O6: =IF(LEFT(E6,1)="f","F","M") -> F | P6: =IF(EXACT(E6,O6)=TRUE,"-","Corrected Errors") -> Corrected Errors | Q6: =UPPER(LEFT(B6,1)) -> S
A7: 6 | B7: Veronika | C7: Lundy | D7: Miss | E7: F | F7: 90 | G7: Katherine Gardens | H7: Ardgay | I7: 40316 | J7: 37 | K7: A3 | M7: =PROPER(Portfolio4346[[#This Row],[Last Name]]) -> Lundy | N7: =IF(EXACT(C7,M7)=TRUE, "-", "Corrected to Title Case") -> - | O7: =IF(LEFT(E7,1)="f","F","M") -> F | P7: =IF(EXACT(E7,O7)=TRUE,"-","Corrected Errors") -> - | Q7: =UPPER(LEFT(B7,1)) -> V | S7: To calculate the number of records affected we used IF & EXACT function
A8: 7 | B8: Valeria | C8: Frost | D8: Mrs | E8: F | F8: 30 | G8: Ross Way | H8: Solihull | I8: 40202 | J8: 12 | K8: C2 | M8: =PROPER(Portfolio4346[[#This Row],[Last Name]]) -> Frost | N8: =IF(EXACT(C8,M8)=TRUE, "-", "Corrected to Title Case") -> - | O8: =IF(LEFT(E8,1)="f","F","M") -> F | P8: =IF(EXACT(E8,O8)=TRUE,"-","Corrected Errors") -> - | Q8: =UPPER(LEFT(B8,1)) -> V | S8: Formula: =IF(EXACT(C2,M2)=TRUE, "-", "Corrected to Title Case")
A9: 8 | B9: Randa | C9: Woods | D9: Mrs | E9: F | F9: 30 | G9: Artisans Dwellings | H9: Tring | I9: 40497 | J9: 55 | K9: C1 | M9: =PROPER(Portfolio4346[[#This Row],[Last Name]]) -> Woods | N9: =IF(EXACT(C9,M9)=TRUE, "-", "Corrected to Title Case") -> - | O9: =IF(LEFT(E9,1)="f","F","M") -> F | P9: =IF(EXACT(E9,O9)=TRUE,"-","Corrected Errors") -> - | Q9: =UPPER(LEFT(B9,1)) -> R
A10: 9 | B10: Karole | C10: Navarro | D10: Mrs | E10: F | F10: 30 | G10: Rhoda Street | H10: St. Ives | I10: 39938 | J10: 10 | K10: C3 | M10: =PROPER(Portfolio4346[[#This Row],[Last Name]]) -> Navarro | N10: =IF(EXACT(C10,M10)=TRUE, "-", "Corrected to Title Case") -> - | O10: =IF(LEFT(E10,1)="f","F","M") -> F | P10: =IF(EXACT(E10,O10)=TRUE,"-","Corrected Errors") -> - | Q10: =UPPER(LEFT(B10,1)) -> K | S10: Then we count the number of records affected using COUNTIF function
A11: 10 | B11: Martin | C11: Anthony | D11: Miss | E11: F | F11: 90 | G11: Iceland Road | H11: Campbeltown | I11: 40466 | J11: 76 | K11: A2 | M11: =PROPER(Portfolio4346[[#This Row],[Last Name]]) -> Anthony | N11: =IF(EXACT(C11,M11)=TRUE, "-", "Corrected to Title Case") -> - | O11: =IF(LEFT(E11,1)="f","F","M") -> F | P11: =IF(EXACT(E11,O11)=TRUE,"-","Corrected Errors") -> - | Q11: =UPPER(LEFT(B11,1)) -> M | S11: Count of Affected records | U11: =COUNTIF(Table6[Records Affected],"Corrected to Title Case") -> 11
A12: 11 | B12: Shanae | C12: Roland | D12: Mrs | E12: F | F12: 90 | G12: Samels Court | H12: Newbridge | I12: 40031 | J12: 28 | K12: C2 | M12: =PROPER(Portfolio4346[[#This Row],[Last Name]]) -> Roland | N12: =IF(EXACT(C12,M12)=TRUE, "-", "Corrected to Title Case") -> - | O12: =IF(LEFT(E12,1)="f","F","M") -> F | P12: =IF(EXACT(E12,O12)=TRUE,"-","Corrected Errors") -> - | Q12: =UPPER(LEFT(B12,1)) -> S
A13: 12 | B13: Yen | C13: Culver | D13: Miss | E13: F | F13: 60 | G13: Garratt Green | H13: London | I13: 39965 | J13: 41 | K13: A2 | M13: =PROPER(Portfolio4346[[#This Row],[Last Name]]) -> Culver | N13: =IF(EXACT(C13,M13)=TRUE, "-", "Corrected to Title Case") -> - | O13: =IF(LEFT(E13,1)="f","F","M") -> F | P13: =IF(EXACT(E13,O13)=TRUE,"-","Corrected Errors") -> - | Q13: =UPPER(LEFT(B13,1)) -> Y
A14: 13 | B14: Monica | C14: Doran | D14: Miss | E14: F | F14: 90 | G14: High St | H14: Caldicot | I14: 39516 | J14: 48 | K14: B | M14: =PROPER(Portfolio4346[[#This Row],[Last Name]]) -> Doran | N14: =IF(EXACT(C14,M14)=TRUE, "-", "Corrected to Title Case") -> - | O14: =IF(LEFT(E14,1)="f","F","M") -> F | P14: =IF(EXACT(E14,O14)=TRUE,"-","Corrected Errors") -> - | Q14: =UPPER(LEFT(B14,1)) -> M | S14: 2. Created one more column for "Gender Correction"
A15: 14 | B15: Laureen | C15: Richards | D15: Prof | E15: F | F15: 90 | G15: Brackenfield Close | H15: Broseley | I15: 39665 | J15: 34 | K15: C4 | M15: =PROPER(Portfolio4346[[#This Row],[Last Name]]) -> Richards | N15: =IF(EXACT(C15,M15)=TRUE, "-", "Corrected to Title Case") -> - | O15: =IF(LEFT(E15,1)="f","F","M") -> F | P15: =IF(EXACT(E15,O15)=TRUE,"-","Corrected Errors") -> - | Q15: =UPPER(LEFT(B15,1)) -> L | S15: Used IF & LEFT function to correct the errors in Gender column
A16: 15 | B16: Meta | C16: Wright | D16: Mrs | E16: F | F16: 60 | G16: Bearstead Rise | H16: Y Felinheli | I16: 40337 | J16: 57 | K16: C4 | M16: =PROPER(Portfolio4346[[#This Row],[Last Name]]) -> Wright | N16: =IF(EXACT(C16,M16)=TRUE, "-", "Corrected to Title Case") -> - | O16: =IF(LEFT(E16,1)="f","F","M") -> F | P16: =IF(EXACT(E16,O16)=TRUE,"-","Corrected Errors") -> - | Q16: =UPPER(LEFT(B16,1)) -> M | S16: Formula: =IF(LEFT(E3,1)="f","F","M")
A17: 16 | B17: Bobbye | C17: Vasquez | D17: Mrs | E17: F | F17: 30 | G17: Baker Road | H17: Trowbridge | I17: 40532 | J17: 59 | K17: E | M17: =PROPER(Portfolio4346[[#This Row],[Last Name]]) -> Vasquez | N17: =IF(EXACT(C17,M17)=TRUE, "-", "Corrected to Title Case") -> - | O17: =IF(LEFT(E17,1)="f","F","M") -> F | P17: =IF(EXACT(E17,O17)=TRUE,"-","Corrected Errors") -> - | Q17: =UPPER(LEFT(B17,1)) -> B
A18: 17 | B18: Emily | C18: Butler | D18: Miss | E18: F | F18: 30 | G18: Telford Close | H18: Isles Of Scilly | I18: 40271 | J18: 84 | K18: C1 | M18: =PROPER(Portfolio4346[[#This Row],[Last Name]]) -> Butler | N18: =IF(EXACT(C18,M18)=TRUE, "-", "Corrected to Title Case") -> - | O18: =IF(LEFT(E18,1)="f","F","M") -> F | P18: =IF(EXACT(E18,O18)=TRUE,"-","Corrected Errors") -> - | Q18: =UPPER(LEFT(B18,1)) -> E | S18: Again to calculate the number of records affected we used IF & EXACT function
A19: 18 | B19: Iona | C19: Hutchinson | D19: Ms | E19: F | F19: 30 | G19: Queens Buildings | H19: Kilmacolm | I19: 40183 | J19: 39 | K19: C4 | M19: =PROPER(Portfolio4346[[#This Row],[Last Name]]) -> Hutchinson | N19: =IF(EXACT(C19,M19)=TRUE, "-", "Corrected to Title Case") -> - | O19: =IF(LEFT(E19,1)="f","F","M") -> F | P19: =IF(EXACT(E19,O19)=TRUE,"-","Corrected Errors") -> - | Q19: =UPPER(LEFT(B19,1)) -> I | S19: Formula: =IF(EXACT(E3,O3)=TRUE,"-","Corrected Errors")
A20: 19 | B20: Windy | C20: Cabrera | D20: Miss | E20: F | F20: 90 | G20: Havelock Cottages | H20: Bridgwater | I20: 40381 | J20: 54 | K20: A1 | M20: =PROPER(Portfolio4346[[#This Row],[Last Name]]) -> Cabrera | N20: =IF(EXACT(C20,M20)=TRUE, "-", "Corrected to Title Case") -> - | O20: =IF(LEFT(E20,1)="f","F","M") -> F | P20: =IF(EXACT(E20,O20)=TRUE,"-","Corrected Errors") -> - | Q20: =UPPER(LEFT(B20,1)) -> W
A21: 20 | B21: Cherry | C21: Walsh | D21: Mrs | E21: F | F21: 90 | G21: Huntingdon Gardens | H21: Essex | I21: 40469 | J21: 33 | K21: C2 | M21: =PROPER(Portfolio4346[[#This Row],[Last Name]]) -> Walsh | N21: =IF(EXACT(C21,M21)=TRUE, "-", "Corrected to Title Case") -> - | O21: =IF(LEFT(E21,1)="f","F","M") -> F | P21: =IF(EXACT(E21,O21)=TRUE,"-","Corrected Errors") -> - | Q21: =UPPER(LEFT(B21,1)) -> C | S21: Then we count the number of Records affected using COUNTIF function
A22: 21 | B22: Jaye | C22: FARLEY | D22: Mrs | E22: F | F22: 60 | G22: Embankment Gardens | H22: Badminton | I22: 39587 | J22: 84 | K22: C2 | M22: =PROPER(Portfolio4346[[#This Row],[Last Name]]) -> Farley | N22: =IF(EXACT(C22,M22)=TRUE, "-", "Corrected to Title Case") -> Corrected to Title Case | O22: =IF(LEFT(E22,1)="f","F","M") -> F | P22: =IF(EXACT(E22,O22)=TRUE,"-","Corrected Errors") -> - | Q22: =UPPER(LEFT(B22,1)) -> J | S22: Count of Affected records | U22: =COUNTIF(Table6[Records Affected2],"Corrected Errors") -> 35
A23: 22 | B23: Garnet | C23: Tipton | D23: Miss | E23: F | F23: 30 | G23: Burton Grove | H23: Halesowen | I23: 39993 | J23: 94 | K23: C1 | M23: =PROPER(Portfolio4346[[#This Row],[Last Name]]) -> Tipton | N23: =IF(EXACT(C23,M23)=TRUE, "-", "Corrected to Title Case") -> - | O23: =IF(LEFT(E23,1)="f","F","M") -> F | P23: =IF(EXACT(E23,O23)=TRUE,"-","Corrected Errors") -> - | Q23: =UPPER(LEFT(B23,1)) -> G
A24: 23 | B24: Coral | C24: Grace | D24: Miss | E24: F | F24: 90 | G24: Alliance Road | H24: Kyle | I24: 40470 | J24: 84 | K24: A1 | M24: =PROPER(Portfolio4346[[#This Row],[Last Name]]) -> Grace | N24: =IF(EXACT(C24,M24)=TRUE, "-", "Corrected to Title Case") -> - | O24: =IF(LEFT(E24,1)="f","F","M") -> F | P24: =IF(EXACT(E24,O24)=TRUE,"-","Corrected Errors") -> - | Q24: =UPPER(LEFT(B24,1)) -> C
A25: 24 | B25: Kacy | C25: Ragland | D25: Miss | E25: F | F25: 90 | G25: Coningsby Cottages | H25: Cradley Heath | I25: 40052 | J25: 37 | K25: A3 | M25: =PROPER(Portfolio4346[[#This Row],[Last Name]]) -> Ragland | N25: =IF(EXACT(C25,M25)=TRUE, "-", "Corrected to Title Case") -> - | O25: =IF(LEFT(E25,1)="f","F","M") -> F | P25: =IF(EXACT(E25,O25)=TRUE,"-","Corrected Errors") -> - | Q25: =UPPER(LEFT(B25,1)) -> K | S25: 3. Added one more column to show "Initials"
A26: 25 | B26: Riva | C26: Crosby | D26: Miss | E26: F | F26: 60 | G26: Burdett Place | H26: Frizington | I26: 40006 | J26: 3 | K26: C2 | M26: =PROPER(Portfolio4346[[#This Row],[Last Name]]) -> Crosby | N26: =IF(EXACT(C26,M26)=TRUE, "-", "Corrected to Title Case") -> - | O26: =IF(LEFT(E26,1)="f","F","M") -> F | P26: =IF(EXACT(E26,O26)=TRUE,"-","Corrected Errors") -> - | Q26: =UPPER(LEFT(B26,1)) -> R | S26: Used the UPPER & LEFT function to show only Initials in the First name column
A27: 26 | B27: Thi | C27: Stroud | D27: Mrs | E27: F | F27: 30 | G27: Biddenden Way | H27: Longfield | I27: 39893 | J27: 34 | K27: C1 | M27: =PROPER(Portfolio4346[[#This Row],[Last Name]]) -> Stroud | N27: =IF(EXACT(C27,M27)=TRUE, "-", "Corrected to Title Case") -> - | O27: =IF(LEFT(E27,1)="f","F","M") -> F | P27: =IF(EXACT(E27,O27)=TRUE,"-","Corrected Errors") -> - | Q27: =UPPER(LEFT(B27,1)) -> T | S27: Formula: =UPPER(LEFT(B2,1))
A28: 27 | B28: Ji | C28: Austin | D28: Mrs | E28: F | F28: 30 | G28: Selhurst Road | H28: Downham Market | I28: 40308 | J28: 78 | K28: A3 | M28: =PROPER(Portfolio4346[[#This Row],[Last Name]]) -> Austin | N28: =IF(EXACT(C28,M28)=TRUE, "-", "Corrected to Title Case") -> - | O28: =IF(LEFT(E28,1)="f","F","M") -> F | P28: =IF(EXACT(E28,O28)=TRUE,"-","Corrected Errors") -> - | Q28: =UPPER(LEFT(B28,1)) -> J
A29: 28 | B29: Molly | C29: MARCUS | D29: Mrs | E29: F | F29: 90 | G29: Lyons Yard | H29: Lyme Regis | I29: 39916 | J29: 46 | K29: A3 | M29: =PROPER(Portfolio4346[[#This Row],[Last Name]]) -> Marcus | N29: =IF(EXACT(C29,M29)=TRUE, "-", "Corrected to Title Case") -> Corrected to Title Case | O29: =IF(LEFT(E29,1)="f","F","M") -> F | P29: =IF(EXACT(E29,O29)=TRUE,"-","Corrected Errors") -> - | Q29: =UPPER(LEFT(B29,1)) -> M | S29: Note: This Sheet is Password Protected, To unlock this sheet use "qwer" as password
A30: 29 | B30: Alina | C30: Pryor | D30: Ms | E30: F | F30: 90 | G30: Edgar Road | H30: Cornwall | I30: 39906 | J30: 34 | K30: E | M30: =PROPER(Portfolio4346[[#This Row],[Last Name]]) -> Pryor | N30: =IF(EXACT(C30,M30)=TRUE, "-", "Corrected to Title Case") -> - | O30: =IF(LEFT(E30,1)="f","F","M") -> F | P30: =IF(EXACT(E30,O30)=TRUE,"-","Corrected Errors") -> - | Q30: =UPPER(LEFT(B30,1)) -> A
A31: 30 | B31: Jo | C31: Simons | D31: Mrs | E31: F | F31: 30 | G31: Roe Lane | H31: Pentre | I31: 39670 | J31: 64 | K31: E | M31: =PROPER(Portfolio4346[[#This Row],[Last Name]]) -> Simons | N31: =IF(EXACT(C31,M31)=TRUE, "-", "Corrected to Title Case") -> - | O31: =IF(LEFT(E31,1)="f","F","M") -> F | P31: =IF(EXACT(E31,O31)=TRUE,"-","Corrected Errors") -> - | Q31: =UPPER(LEFT(B31,1)) -> J
A32: 31 | B32: Lacy | C32: Emerson | D32: Miss | E32: F | F32: 90 | G32: Beaufort Wharf | H32: Cirencester | I32: 39552 | J32: 80 | K32: D | M32: =PROPER(Portfolio4346[[#This Row],[Last Name]]) -> Emerson | N32: =IF(EXACT(C32,M32)=TRUE, "-", "Corrected to Title Case") -> - | O32: =IF(LEFT(E32,1)="f","F","M") -> F | P32: =IF(EXACT(E32,O32)=TRUE,"-","Corrected Errors") -> - | Q32: =UPPER(LEFT(B32,1)) -> L
A33: 32 | B33: Janice | C33: Oneal | D33: Miss | E33: F | F33: 60 | G33: Anns Close | H33: Ellesmere | I33: 40508 | J33: 88 | K33: B | M33: =PROPER(Portfolio4346[[#This Row],[Last Name]]) -> Oneal | N33: =IF(EXACT(C33,M33)=TRUE, "-", "Corrected to Title Case") -> - | O33: =IF(LEFT(E33,1)="f","F","M") -> F | P33: =IF(EXACT(E33,O33)=TRUE,"-","Corrected Errors") -> - | Q33: =UPPER(LEFT(B33,1)) -> J
A34: 33 | B34: Donella | C34: Fenton | D34: Miss | E34: F | F34: 90 | G34: Sladedale Road | H34: Newnham | I34: 39534 | J34: 60 | K34: E | M34: =PROPER(Portfolio4346[[#This Row],[Last Name]]) -> Fenton | N34: =IF(EXACT(C34,M34)=TRUE, "-", "Corrected to Title Case") -> - | O34: =IF(LEFT(E34,1)="f","F","M") -> F | P34: =IF(EXACT(E34,O34)=TRUE,"-","Corrected Errors") -> - | Q34: =UPPER(LEFT(B34,1)) -> D
A35: 34 | B35: Jacinta | C35: Blackburn | D35: Mrs | E35: F | F35: 30 | G35: Falkland Place | H35: Ascot | I35: 39746 | J35: 22 | K35: C1 | M35: =PROPER(Portfolio4346[[#This Row],[Last Name]]) -> Blackburn | N35: =IF(EXACT(C35,M35)=TRUE, "-", "Corrected to Title Case") -> - | O35: =IF(LEFT(E35,1)="f","F","M") -> F | P35: =IF(EXACT(E35,O35)=TRUE,"-","Corrected Errors") -> - | Q35: =UPPER(LEFT(B35,1)) -> J
A36: 35 | B36: Chasity | C36: Mcfadden | D36: Miss | E36: F | F36: 60 | G36: Westdean Close | H36: Ardgay | I36: 39449 | J36: 99 | K36: A1 | M36: =PROPER(Portfolio4346[[#This Row],[Last Name]]) -> Mcfadden | N36: =IF(EXACT(C36,M36)=TRUE, "-", "Corrected to Title Case") -> - | O36: =IF(LEFT(E36,1)="f","F","M") -> F | P36: =IF(EXACT(E36,O36)=TRUE,"-","Corrected Errors") -> - | Q36: =UPPER(LEFT(B36,1)) -> C
A37: 36 | B37: Margot | C37: Akers | D37: Miss | E37: F | F37: 30 | G37: Roslyn Avenue | H37: Tidworth | I37: 40442 | J37: 94 | K37: A1 | M37: =PROPER(Portfolio4346[[#This Row],[Last Name]]) -> Akers | N37: =IF(EXACT(C37,M37)=TRUE, "-", "Corrected to Title Case") -> - | O37: =IF(LEFT(E37,1)="f","F","M") -> F | P37: =IF(EXACT(E37,O37)=TRUE,"-","Corrected Errors") -> - | Q37: =UPPER(LEFT(B37,1)) -> M
A38: 37 | B38: Tresa | C38: Meza | D38: Mrs | E38: F | F38: 90 | G38: East Mount | H38: Llandinam | I38: 40452 | J38: 3 | K38: B | M38: =PROPER(Portfolio4346[[#This Row],[Last Name]]) -> Meza | N38: =IF(EXACT(C38,M38)=TRUE, "-", "Corrected to Title Case") -> - | O38: =IF(LEFT(E38,1)="f","F","M") -> F | P38: =IF(EXACT(E38,O38)=TRUE,"-","Corrected Errors") -> - | Q38: =UPPER(LEFT(B38,1)) -> T
A39: 38 | B39: Jack | C39: Johnston | D39: Mrs | E39: F | F39: 60 | G39: Grainger Street | H39: Christchurch | I39: 39530 | J39: 16 | K39: A1 | M39: =PROPER(Portfolio4346[[#This Row],[Last Name]]) -> Johnston | N39: =IF(EXACT(C39,M39)=TRUE, "-", "Corrected to Title Case") -> - | O39: =IF(LEFT(E39,1)="f","F","M") -> F | P39: =IF(EXACT(E39,O39)=TRUE,"-","Corrected Errors") -> - | Q39: =UPPER(LEFT(B39,1)) -> J
A40: 39 | B40: Kaley | C40: Kay | D40: Mrs | E40: F | F40: 90 | G40: Upper Paget | H40: Cheshire | I40: 40098 | J40: 57 | K40: C4 | M40: =PROPER(Portfolio4346[[#This Row],[Last Name]]) -> Kay | N40: =IF(EXACT(C40,M40)=TRUE, "-", "Corrected to Title Case") -> - | O40: =IF(LEFT(E40,1)="f","F","M") -> F | P40: =IF(EXACT(E40,O40)=TRUE,"-","Corrected Errors") -> - | Q40: =UPPER(LEFT(B40,1)) -> K
A41: 40 | B41: Shaniqua | C41: Baker | D41: Miss | E41: F | F41: 30 | G41: Claypole Road | H41: Lancaster | I41: 40337 | J41: 44 | K41: C1 | M41: =PROPER(Portfolio4346[[#This Row],[Last Name]]) -> Baker | N41: =IF(EXACT(C41,M41)=TRUE, "-", "Corrected to Title Case") -> - | O41: =IF(LEFT(E41,1)="f","F","M") -> F | P41: =IF(EXACT(E41,O41)=TRUE,"-","Corrected Errors") -> - | Q41: =UPPER(LEFT(B41,1)) -> S
... A1987: 2000 | B1987: Gaston | C1987: Guy | D1987: Mr | E1987: M | F1987: 60 | G1987: Wansbeck Road | H1987: Ledbury | I1987: 40301 | J1987: 58 | K1987: D | M1987: =PROPER(Portfolio4346[[#This Row],[Last Name]]) -> Guy | N1987: =IF(EXACT(C1987,M1987)=TRUE, "-", "Corrected to Title Case") -> - | O1987: =IF(LEFT(E1987,1)="f","F","M") -> M | P1987: =IF(EXACT(E1987,O1987)=TRUE,"-","Corrected Errors") -> - | Q1987: =UPPER(LEFT(B1987,1)) -> G

Sheet Task 4.3
A1: ID | B1: First Name | C1: Last Name | D1: Title | E1: Gender | F1: Credit | G1: Street | H1: Town | I1: Order Date | J1: Quantity | K1: Product | L1: Product Name | M1: Order Quantity | N1: Order Value | O1: Year | P1: Month
A2: 1 | B2: =Table6[[#This Row],[Initials]] -> N | C2: =Table6[[#This Row],[Last Name Correction]] -> Camp | D2: Mrs | E2: =Table6[[#This Row],[Gender Correction]] -> F | F2: 60 | G2: Rosmore Road | H2: Berkeley | I2: 39988 | J2: 13 | K2: A1 | L2: =VLOOKUP(Portfolio43468[[#This Row],[Product]],ProductName,2) -> Megawidget S | M2: =VLOOKUP(K2,ProductName,4)*J2 -> 312 | N2: =VLOOKUP(K2,ProductName,3)*M2 -> 246.48 | O2: =YEAR(I2) -> 2009 | P2: =TEXT(I2,"MMM") -> Jun | R2: Lookup Table | X2: STEPS
A3: 2 | B3: =Table6[[#This Row],[Initials]] -> E | C3: =Table6[[#This Row],[Last Name Correction]] -> Dorsey | D3: Mrs | E3: =Table6[[#This Row],[Gender Correction]] -> F | F3: 90 | G3: Roxwell Road | H3: Glossop | I3: 39770 | J3: 14 | K3: C3 | L3: =VLOOKUP(Portfolio43468[[#This Row],[Product]],ProductName,2) -> Ultrathing V3 | M3: =VLOOKUP(K3,ProductName,4)*J3 -> 336 | N3: =VLOOKUP(K3,ProductName,3)*M3 -> 1172.64 | O3: =YEAR(I3) -> 2008 | P3: =TEXT(I3,"MMM") -> Nov | R3: Code | S3: Item | T3: Cost | U3: Case Size | X3: Created a lookup table to calculate Product Name, Order Quantity & Order Value
A4: 3 | B4: =Table6[[#This Row],[Initials]] -> A | C4: =Table6[[#This Row],[Last Name Correction]] -> Devine | D4: Mrs | E4: =Table6[[#This Row],[Gender Correction]] -> F | F4: 60 | G4: Ashbury Place | H4: Immingham | I4: 39895 | J4: 23 | K4: E | L4: =VLOOKUP(Portfolio43468[[#This Row],[Product]],ProductName,2) -> Superwossname | M4: =VLOOKUP(K4,ProductName,4)*J4 -> 460 | N4: =VLOOKUP(K4,ProductName,3)*M4 -> 1430.6 | O4: =YEAR(I4) -> 2009 | P4: =TEXT(I4,"MMM") -> Mar | R4: A1 | S4: Megawidget S | T4: 0.79 | U4: 24 | X4: Formulas Used: | Z4: VLOOKUP([@Product],ProductName,2)
A5: 4 | B5: =Table6[[#This Row],[Initials]] -> N | C5: =Table6[[#This Row],[Last Name Correction]] -> Washington | D5: Miss | E5: =Table6[[#This Row],[Gender Correction]] -> F | F5: 60 | G5: Grafton Road | H5: Broadstone | I5: 39830 | J5: 79 | K5: E | L5: =VLOOKUP(Portfolio43468[[#This Row],[Product]],ProductName,2) -> Superwossname | M5: =VLOOKUP(K5,ProductName,4)*J5 -> 1580 | N5: =VLOOKUP(K5,ProductName,3)*M5 -> 4913.8 | O5: =YEAR(I5) -> 2009 | P5: =TEXT(I5,"MMM") -> Jan | R5: A2 | S5: Megawidget M | T5: 1.19 | U5: 24 | Z5: VLOOKUP(K2,ProductName,4)*J2
A6: 5 | B6: =Table6[[#This Row],[Initials]] -> S | C6: =Table6[[#This Row],[Last Name Correction]] -> Hedrick | D6: Miss | E6: =Table6[[#This Row],[Gender Correction]] -> F | F6: 60 | G6: Beechdale Road | H6: Port Talbot | I6: 39988 | J6: 44 | K6: C3 | L6: =VLOOKUP(Portfolio43468[[#This Row],[Product]],ProductName,2) -> Ultrathing V3 | M6: =VLOOKUP(K6,ProductName,4)*J6 -> 1056 | N6: =VLOOKUP(K6,ProductName,3)*M6 -> 3685.44 | O6: =YEAR(I6) -> 2009 | P6: =TEXT(I6,"MMM") -> Jun | R6: A3 | S6: Megawidget L | T6: 1.59 | U6: 24 | Z6: VLOOKUP(K3,ProductName,3)*M3
A7: 6 | B7: =Table6[[#This Row],[Initials]] -> V | C7: =Table6[[#This Row],[Last Name Correction]] -> Lundy | D7: Miss | E7: =Table6[[#This Row],[Gender Correction]] -> F | F7: 90 | G7: Katherine Gardens | H7: Ardgay | I7: 40316 | J7: 37 | K7: A3 | L7: =VLOOKUP(Portfolio43468[[#This Row],[Product]],ProductName,2) -> Megawidget L | M7: =VLOOKUP(K7,ProductName,4)*J7 -> 888 | N7: =VLOOKUP(K7,ProductName,3)*M7 -> 1411.92 | O7: =YEAR(I7) -> 2010 | P7: =TEXT(I7,"MMM") -> May | R7: B | S7: Hyperwotsit | T7: 2.01 | U7: 20
A8: 7 | B8: =Table6[[#This Row],[Initials]] -> V | C8: =Table6[[#This Row],[Last Name Correction]] -> Frost | D8: Mrs | E8: =Table6[[#This Row],[Gender Correction]] -> F | F8: 30 | G8: Ross Way | H8: Solihull | I8: 40202 | J8: 12 | K8: C2 | L8: =VLOOKUP(Portfolio43468[[#This Row],[Product]],ProductName,2) -> Ultrathing V2 | M8: =VLOOKUP(K8,ProductName,4)*J8 -> 240 | N8: =VLOOKUP(K8,ProductName,3)*M8 -> 717.6 | O8: =YEAR(I8) -> 2010 | P8: =TEXT(I8,"MMM") -> Jan | R8: C1 | S8: Ultrathing V1 | T8: 1.99 | U8: 17
A9: 8 | B9: =Table6[[#This Row],[Initials]] -> R | C9: =Table6[[#This Row],[Last Name Correction]] -> Woods | D9: Mrs | E9: =Table6[[#This Row],[Gender Correction]] -> F | F9: 30 | G9: Artisans Dwellings | H9: Tring | I9: 40497 | J9: 55 | K9: C1 | L9: =VLOOKUP(Portfolio43468[[#This Row],[Product]],ProductName,2) -> Ultrathing V1 | M9: =VLOOKUP(K9,ProductName,4)*J9 -> 935 | N9: =VLOOKUP(K9,ProductName,3)*M9 -> 1860.65 | O9: =YEAR(I9) -> 2010 | P9: =TEXT(I9,"MMM") -> Nov | R9: C2 | S9: Ultrathing V2 | T9: 2.99 | U9: 20
A10: 9 | B10: =Table6[[#This Row],[Initials]] -> K | C10: =Table6[[#This Row],[Last Name Correction]] -> Navarro | D10: Mrs | E10: =Table6[[#This Row],[Gender Correction]] -> F | F10: 30 | G10: Rhoda Street | H10: St. Ives | I10: 39938 | J10: 10 | K10: C3 | L10: =VLOOKUP(Portfolio43468[[#This Row],[Product]],ProductName,2) -> Ultrathing V3 | M10: =VLOOKUP(K10,ProductName,4)*J10 -> 240 | N10: =VLOOKUP(K10,ProductName,3)*M10 -> 837.6 | O10: =YEAR(I10) -> 2009 | P10: =TEXT(I10,"MMM") -> May | R10: C3 | S10: Ultrathing V3 | T10: 3.49 | U10: 24
A11: 10 | B11: =Table6[[#This Row],[Initials]] -> M | C11: =Table6[[#This Row],[Last Name Correction]] -> Anthony | D11: Miss | E11: =Table6[[#This Row],[Gender Correction]] -> F | F11: 90 | G11: Iceland Road | H11: Campbeltown | I11: 40466 | J11: 76 | K11: A2 | L11: =VLOOKUP(Portfolio43468[[#This Row],[Product]],ProductName,2) -> Megawidget M | M11: =VLOOKUP(K11,ProductName,4)*J11 -> 1824 | N11: =VLOOKUP(K11,ProductName,3)*M11 -> 2170.56 | O11: =YEAR(I11) -> 2010 | P11: =TEXT(I11,"MMM") -> Oct | R11: C4 | S11: Ultrathing V4 | T11: 3.99 | U11: 24
A12: 11 | B12: =Table6[[#This Row],[Initials]] -> S | C12: =Table6[[#This Row],[Last Name Correction]] -> Roland | D12: Mrs | E12: =Table6[[#This Row],[Gender Correction]] -> F | F12: 90 | G12: Samels Court | H12: Newbridge | I12: 40031 | J12: 28 | K12: C2 | L12: =VLOOKUP(Portfolio43468[[#This Row],[Product]],ProductName,2) -> Ultrathing V2 | M12: =VLOOKUP(K12,ProductName,4)*J12 -> 560 | N12: =VLOOKUP(K12,ProductName,3)*M12 -> 1674.4 | O12: =YEAR(I12) -> 2009 | P12: =TEXT(I12,"MMM") -> Aug | R12: D | S12: Gigastuff | T12: 1.89 | U12: 18
A13: 12 | B13: =Table6[[#This Row],[Initials]] -> Y | C13: =Table6[[#This Row],[Last Name Correction]] -> Culver | D13: Miss | E13: =Table6[[#This Row],[Gender Correction]] -> F | F13: 60 | G13: Garratt Green | H13: London | I13: 39965 | J13: 41 | K13: A2 | L13: =VLOOKUP(Portfolio43468[[#This Row],[Product]],ProductName,2) -> Megawidget M | M13: =VLOOKUP(K13,ProductName,4)*J13 -> 984 | N13: =VLOOKUP(K13,ProductName,3)*M13 -> 1170.96 | O13: =YEAR(I13) -> 2009 | P13: =TEXT(I13,"MMM") -> Jun | R13: E | S13: Superwossname | T13: 3.11 | U13: 20
A14: 13 | B14: =Table6[[#This Row],[Initials]] -> M | C14: =Table6[[#This Row],[Last Name Correction]] -> Doran | D14: Miss | E14: =Table6[[#This Row],[Gender Correction]] -> F | F14: 90 | G14: High St | H14: Caldicot | I14: 39516 | J14: 48 | K14: B | L14: =VLOOKUP(Portfolio43468[[#This Row],[Product]],ProductName,2) -> Hyperwotsit | M14: =VLOOKUP(K14,ProductName,4)*J14 -> 960 | N14: =VLOOKUP(K14,ProductName,3)*M14 -> 1929.6 | O14: =YEAR(I14) -> 2008 | P14: =TEXT(I14,"MMM") -> Mar
A15: 14 | B15: =Table6[[#This Row],[Initials]] -> L | C15: =Table6[[#This Row],[Last Name Correction]] -> Richards | D15: Prof | E15: =Table6[[#This Row],[Gender Correction]] -> F | F15: 90 | G15: Brackenfield Close | H15: Broseley | I15: 39665 | J15: 34 | K15: C4 | L15: =VLOOKUP(Portfolio43468[[#This Row],[Product]],ProductName,2) -> Ultrathing V4 | M15: =VLOOKUP(K15,ProductName,4)*J15 -> 816 | N15: =VLOOKUP(K15,ProductName,3)*M15 -> 3255.84 | O15: =YEAR(I15) -> 2008 | P15: =TEXT(I15,"MMM") -> Aug
A16: 15 | B16: =Table6[[#This Row],[Initials]] -> M | C16: =Table6[[#This Row],[Last Name Correction]] -> Wright | D16: Mrs | E16: =Table6[[#This Row],[Gender Correction]] -> F | F16: 60 | G16: Bearstead Rise | H16: Y Felinheli | I16: 40337 | J16: 57 | K16: C4 | L16: =VLOOKUP(Portfolio43468[[#This Row],[Product]],ProductName,2) -> Ultrathing V4 | M16: =VLOOKUP(K16,ProductName,4)*J16 -> 1368 | N16: =VLOOKUP(K16,ProductName,3)*M16 -> 5458.32 | O16: =YEAR(I16) -> 2010 | P16: =TEXT(I16,"MMM") -> Jun | R16: Method 1: Using SUMIFS Formula
A17: 16 | B17: =Table6[[#This Row],[Initials]] -> B | C17: =Table6[[#This Row],[Last Name Correction]] -> Vasquez | D17: Mrs | E17: =Table6[[#This Row],[Gender Correction]] -> F | F17: 30 | G17: Baker Road | H17: Trowbridge | I17: 40532 | J17: 59 | K17: E | L17: =VLOOKUP(Portfolio43468[[#This Row],[Product]],ProductName,2) -> Superwossname | M17: =VLOOKUP(K17,ProductName,4)*J17 -> 1180 | N17: =VLOOKUP(K17,ProductName,3)*M17 -> 3669.8 | O17: =YEAR(I17) -> 2010 | P17: =TEXT(I17,"MMM") -> Dec
A18: 17 | B18: =Table6[[#This Row],[Initials]] -> E | C18: =Table6[[#This Row],[Last Name Correction]] -> Butler | D18: Miss | E18: =Table6[[#This Row],[Gender Correction]] -> F | F18: 30 | G18: Telford Close | H18: Isles Of Scilly | I18: 40271 | J18: 84 | K18: C1 | L18: =VLOOKUP(Portfolio43468[[#This Row],[Product]],ProductName,2) -> Ultrathing V1 | M18: =VLOOKUP(K18,ProductName,4)*J18 -> 1428 | N18: =VLOOKUP(K18,ProductName,3)*M18 -> 2841.72 | O18: =YEAR(I18) -> 2010 | P18: =TEXT(I18,"MMM") -> Apr | R18: Year | S18: Jan | T18: Feb | U18: Mar | V18: Apr | W18: May | X18: Jun | Y18: Jul | Z18: Aug | AA18: Sep | AB18: Oct | AC18: Nov | AD18: Dec
A19: 18 | B19: =Table6[[#This Row],[Initials]] -> I | C19: =Table6[[#This Row],[Last Name Correction]] -> Hutchinson | D19: Ms | E19: =Table6[[#This Row],[Gender Correction]] -> F | F19: 30 | G19: Queens Buildings | H19: Kilmacolm | I19: 40183 | J19: 39 | K19: C4 | L19: =VLOOKUP(Portfolio43468[[#This Row],[Product]],ProductName,2) -> Ultrathing V4 | M19: =VLOOKUP(K19,ProductName,4)*J19 -> 936 | N19: =VLOOKUP(K19,ProductName,3)*M19 -> 3734.64 | O19: =YEAR(I19) -> 2010 | P19: =TEXT(I19,"MMM") -> Jan | R19: 2008 | S19: =SUMIFS($N$2:$N$1987,$O$2:$O$1987,$R19,$P$2:$P$1987,S$18) -> 153629.38 | T19: =SUMIFS($N$2:$N$1987,$O$2:$O$1987,$R19,$P$2:$P$1987,T$18) -> 83125.81 | U19: =SUMIFS($N$2:$N$1987,$O$2:$O$1987,$R19,$P$2:$P$1987,U$18) -> 131988.34 | V19: =SUMIFS($N$2:$N$1987,$O$2:$O$1987,$R19,$P$2:$P$1987,V$18) -> 115302.47 | W19: =SUMIFS($N$2:$N$1987,$O$2:$O$1987,$R19,$P$2:$P$1987,W$18) -> 142221.6 | X19: =SUMIFS($N$2:$N$1987,$O$2:$O$1987,$R19,$P$2:$P$1987,X$18) -> 150280.49 | Y19: =SUMIFS($N$2:$N$1987,$O$2:$O$1987,$R19,$P$2:$P$1987,Y$18) -> 161701.5 | Z19: =SUMIFS($N$2:$N$1987,$O$2:$O$1987,$R19,$P$2:$P$1987,Z$18) -> 162951.5 | ... AD19: =SUMIFS($N$2:$N$1987,$O$2:$O$1987,$R19,$P$2:$P$1987,AD$18) -> 151056.58
A20: 19 | B20: =Table6[[#This Row],[Initials]] -> W | C20: =Table6[[#This Row],[Last Name Correction]] -> Cabrera | D20: Miss | E20: =Table6[[#This Row],[Gender Correction]] -> F | F20: 90 | G20: Havelock Cottages | H20: Bridgwater | I20: 40381 | J20: 54 | K20: A1 | L20: =VLOOKUP(Portfolio43468[[#This Row],[Product]],ProductName,2) -> Megawidget S | M20: =VLOOKUP(K20,ProductName,4)*J20 -> 1296 | N20: =VLOOKUP(K20,ProductName,3)*M20 -> 1023.84 | O20: =YEAR(I20) -> 2010 | P20: =TEXT(I20,"MMM") -> Jul | R20: 2009 | S20: =SUMIFS($N$2:$N$1987,$O$2:$O$1987,$R20,$P$2:$P$1987,S$18) -> 125774.12 | T20: =SUMIFS($N$2:$N$1987,$O$2:$O$1987,$R20,$P$2:$P$1987,T$18) -> 88773.92 | U20: =SUMIFS($N$2:$N$1987,$O$2:$O$1987,$R20,$P$2:$P$1987,U$18) -> 122300.12 | V20: =SUMIFS($N$2:$N$1987,$O$2:$O$1987,$R20,$P$2:$P$1987,V$18) -> 135559.15 | W20: =SUMIFS($N$2:$N$1987,$O$2:$O$1987,$R20,$P$2:$P$1987,W$18) -> 147963.52 | X20: =SUMIFS($N$2:$N$1987,$O$2:$O$1987,$R20,$P$2:$P$1987,X$18) -> 138723.37 | Y20: =SUMIFS($N$2:$N$1987,$O$2:$O$1987,$R20,$P$2:$P$1987,Y$18) -> 129718.29 | Z20: =SUMIFS($N$2:$N$1987,$O$2:$O$1987,$R20,$P$2:$P$1987,Z$18) -> 123668.96 | ... AD20: =SUMIFS($N$2:$N$1987,$O$2:$O$1987,$R20,$P$2:$P$1987,AD$18) -> 126633.8
A21: 20 | B21: =Table6[[#This Row],[Initials]] -> C | C21: =Table6[[#This Row],[Last Name Correction]] -> Walsh | D21: Mrs | E21: =Table6[[#This Row],[Gender Correction]] -> F | F21: 90 | G21: Huntingdon Gardens | H21: Essex | I21: 40469 | J21: 33 | K21: C2 | L21: =VLOOKUP(Portfolio43468[[#This Row],[Product]],ProductName,2) -> Ultrathing V2 | M21: =VLOOKUP(K21,ProductName,4)*J21 -> 660 | N21: =VLOOKUP(K21,ProductName,3)*M21 -> 1973.4 | O21: =YEAR(I21) -> 2010 | P21: =TEXT(I21,"MMM") -> Oct | R21: 2010 | S21: =SUMIFS($N$2:$N$1987,$O$2:$O$1987,$R21,$P$2:$P$1987,S$18) -> 140157.75 | T21: =SUMIFS($N$2:$N$1987,$O$2:$O$1987,$R21,$P$2:$P$1987,T$18) -> 146532.92 | U21: =SUMIFS($N$2:$N$1987,$O$2:$O$1987,$R21,$P$2:$P$1987,U$18) -> 150135.42 | V21: =SUMIFS($N$2:$N$1987,$O$2:$O$1987,$R21,$P$2:$P$1987,V$18) -> 158124.82 | W21: =SUMIFS($N$2:$N$1987,$O$2:$O$1987,$R21,$P$2:$P$1987,W$18) -> 153677.69 | X21: =SUMIFS($N$2:$N$1987,$O$2:$O$1987,$R21,$P$2:$P$1987,X$18) -> 141835.32 | Y21: =SUMIFS($N$2:$N$1987,$O$2:$O$1987,$R21,$P$2:$P$1987,Y$18) -> 125377.45 | Z21: =SUMIFS($N$2:$N$1987,$O$2:$O$1987,$R21,$P$2:$P$1987,Z$18) -> 103154.58 | ... AD21: =SUMIFS($N$2:$N$1987,$O$2:$O$1987,$R21,$P$2:$P$1987,AD$18) -> 110212.95
A22: 21 | B22: =Table6[[#This Row],[Initials]] -> J | C22: =Table6[[#This Row],[Last Name Correction]] -> Farley | D22: Mrs | E22: =Table6[[#This Row],[Gender Correction]] -> F | F22: 60 | G22: Embankment Gardens | H22: Badminton | I22: 39587 | J22: 84 | K22: C2 | L22: =VLOOKUP(Portfolio43468[[#This Row],[Product]],ProductName,2) -> Ultrathing V2 | M22: =VLOOKUP(K22,ProductName,4)*J22 -> 1680 | N22: =VLOOKUP(K22,ProductName,3)*M22 -> 5023.2 | O22: =YEAR(I22) -> 2008 | P22: =TEXT(I22,"MMM") -> May
A23: 22 | B23: =Table6[[#This Row],[Initials]] -> G | C23: =Table6[[#This Row],[Last Name Correction]] -> Tipton | D23: Miss | E23: =Table6[[#This Row],[Gender Correction]] -> F | F23: 30 | G23: Burton Grove | H23: Halesowen | I23: 39993 | J23: 94 | K23: C1 | L23: =VLOOKUP(Portfolio43468[[#This Row],[Product]],ProductName,2) -> Ultrathing V1 | M23: =VLOOKUP(K23,ProductName,4)*J23 -> 1598 | N23: =VLOOKUP(K23,ProductName,3)*M23 -> 3180.02 | O23: =YEAR(I23) -> 2009 | P23: =TEXT(I23,"MMM") -> Jun | R23: Total Sales By Year | X23: To look at total sales by year and total sales by month we can use 2 methods
A24: 23 | B24: =Table6[[#This Row],[Initials]] -> C | C24: =Table6[[#This Row],[Last Name Correction]] -> Grace | D24: Miss | E24: =Table6[[#This Row],[Gender Correction]] -> F | F24: 90 | G24: Alliance Road | H24: Kyle | I24: 40470 | J24: 84 | K24: A1 | L24: =VLOOKUP(Portfolio43468[[#This Row],[Product]],ProductName,2) -> Megawidget S | M24: =VLOOKUP(K24,ProductName,4)*J24 -> 2016 | N24: =VLOOKUP(K24,ProductName,3)*M24 -> 1592.64 | O24: =YEAR(I24) -> 2010 | P24: =TEXT(I24,"MMM") -> Oct | R24: Year | S24: Total Sales | X24: 1. Using SUMIFS: Made a table listing all Years & Months
A25: 24 | B25: =Table6[[#This Row],[Initials]] -> K | C25: =Table6[[#This Row],[Last Name Correction]] -> Ragland | D25: Miss | E25: =Table6[[#This Row],[Gender Correction]] -> F | F25: 90 | G25: Coningsby Cottages | H25: Cradley Heath | I25: 40052 | J25: 37 | K25: A3 | L25: =VLOOKUP(Portfolio43468[[#This Row],[Product]],ProductName,2) -> Megawidget L | M25: =VLOOKUP(K25,ProductName,4)*J25 -> 888 | N25: =VLOOKUP(K25,ProductName,3)*M25 -> 1411.92 | O25: =YEAR(I25) -> 2009 | P25: =TEXT(I25,"MMM") -> Aug | R25: 2008 | S25: =SUM(S19:AD19) -> 1683780.7 | X25: Formula =SUMIFS($N$2:$N$1987,$O$2:$O$1987,$R19,$P$2:$P$1987,S$18)
A26: 25 | B26: =Table6[[#This Row],[Initials]] -> R | C26: =Table6[[#This Row],[Last Name Correction]] -> Crosby | D26: Miss | E26: =Table6[[#This Row],[Gender Correction]] -> F | F26: 60 | G26: Burdett Place | H26: Frizington | I26: 40006 | J26: 3 | K26: C2 | L26: =VLOOKUP(Portfolio43468[[#This Row],[Product]],ProductName,2) -> Ultrathing V2 | M26: =VLOOKUP(K26,ProductName,4)*J26 -> 60 | N26: =VLOOKUP(K26,ProductName,3)*M26 -> 179.4 | O26: =YEAR(I26) -> 2009 | P26: =TEXT(I26,"MMM") -> Jul | R26: 2009 | S26: =SUM(S20:AD20) -> 1520156.8 | X26: Used SUM function to calculate the Total Sales for 2008,2009,2010
A27: 26 | B27: =Table6[[#This Row],[Initials]] -> T | C27: =Table6[[#This Row],[Last Name Correction]] -> Stroud | D27: Mrs | E27: =Table6[[#This Row],[Gender Correction]] -> F | F27: 30 | G27: Biddenden Way | H27: Longfield | I27: 39893 | J27: 34 | K27: C1 | L27: =VLOOKUP(Portfolio43468[[#This Row],[Product]],ProductName,2) -> Ultrathing V1 | M27: =VLOOKUP(K27,ProductName,4)*J27 -> 578 | N27: =VLOOKUP(K27,ProductName,3)*M27 -> 1150.22 | O27: =YEAR(I27) -> 2009 | P27: =TEXT(I27,"MMM") -> Mar | R27: 2010 | S27: =SUM(S21:AD21) -> 1644229.8
A28: 27 | B28: =Table6[[#This Row],[Initials]] -> J | C28: =Table6[[#This Row],[Last Name Correction]] -> Austin | D28: Mrs | E28: =Table6[[#This Row],[Gender Correction]] -> F | F28: 30 | G28: Selhurst Road | H28: Downham Market | I28: 40308 | J28: 78 | K28: A3 | L28: =VLOOKUP(Portfolio43468[[#This Row],[Product]],ProductName,2) -> Megawidget L | M28: =VLOOKUP(K28,ProductName,4)*J28 -> 1872 | N28: =VLOOKUP(K28,ProductName,3)*M28 -> 2976.48 | O28: =YEAR(I28) -> 2010 | P28: =TEXT(I28,"MMM") -> May | R28: Total | S28: =SUM(Table10[Total Sales]) -> 4848167.3
A29: 28 | B29: =Table6[[#This Row],[Initials]] -> M | C29: =Table6[[#This Row],[Last Name Correction]] -> Marcus | D29: Mrs | E29: =Table6[[#This Row],[Gender Correction]] -> F | F29: 90 | G29: Lyons Yard | H29: Lyme Regis | I29: 39916 | J29: 46 | K29: A3 | L29: =VLOOKUP(Portfolio43468[[#This Row],[Product]],ProductName,2) -> Megawidget L | M29: =VLOOKUP(K29,ProductName,4)*J29 -> 1104 | N29: =VLOOKUP(K29,ProductName,3)*M29 -> 1755.36 | O29: =YEAR(I29) -> 2009 | P29: =TEXT(I29,"MMM") -> Apr
A30: 29 | B30: =Table6[[#This Row],[Initials]] -> A | C30: =Table6[[#This Row],[Last Name Correction]] -> Pryor | D30: Ms | E30: =Table6[[#This Row],[Gender Correction]] -> F | F30: 90 | G30: Edgar Road | H30: Cornwall | I30: 39906 | J30: 34 | K30: E | L30: =VLOOKUP(Portfolio43468[[#This Row],[Product]],ProductName,2) -> Superwossname | M30: =VLOOKUP(K30,ProductName,4)*J30 -> 680 | N30: =VLOOKUP(K30,ProductName,3)*M30 -> 2114.8 | O30: =YEAR(I30) -> 2009 | P30: =TEXT(I30,"MMM") -> Apr
A31: 30 | B31: =Table6[[#This Row],[Initials]] -> J | C31: =Table6[[#This Row],[Last Name Correction]] -> Simons | D31: Mrs | E31: =Table6[[#This Row],[Gender Correction]] -> F | F31: 30 | G31: Roe Lane | H31: Pentre | I31: 39670 | J31: 64 | K31: E | L31: =VLOOKUP(Portfolio43468[[#This Row],[Product]],ProductName,2) -> Superwossname | M31: =VLOOKUP(K31,ProductName,4)*J31 -> 1280 | N31: =VLOOKUP(K31,ProductName,3)*M31 -> 3980.8 | O31: =YEAR(I31) -> 2008 | P31: =TEXT(I31,"MMM") -> Aug | R31: Method 2: Using Pivot Table
A32: 31 | B32: =Table6[[#This Row],[Initials]] -> L | C32: =Table6[[#This Row],[Last Name Correction]] -> Emerson | D32: Miss | E32: =Table6[[#This Row],[Gender Correction]] -> F | F32: 90 | G32: Beaufort Wharf | H32: Cirencester | I32: 39552 | J32: 80 | K32: D | L32: =VLOOKUP(Portfolio43468[[#This Row],[Product]],ProductName,2) -> Gigastuff | M32: =VLOOKUP(K32,ProductName,4)*J32 -> 1440 | N32: =VLOOKUP(K32,ProductName,3)*M32 -> 2721.6 | O32: =YEAR(I32) -> 2008 | P32: =TEXT(I32,"MMM") -> Apr
A33: 32 | B33: =Table6[[#This Row],[Initials]] -> J | C33: =Table6[[#This Row],[Last Name Correction]] -> Oneal | D33: Miss | E33: =Table6[[#This Row],[Gender Correction]] -> F | F33: 60 | G33: Anns Close | H33: Ellesmere | I33: 40508 | J33: 88 | K33: B | L33: =VLOOKUP(Portfolio43468[[#This Row],[Product]],ProductName,2) -> Hyperwotsit | M33: =VLOOKUP(K33,ProductName,4)*J33 -> 1760 | N33: =VLOOKUP(K33,ProductName,3)*M33 -> 3537.6 | O33: =YEAR(I33) -> 2010 | P33: =TEXT(I33,"MMM") -> Nov | R33: Row Labels | S33: Sum of Order Value | U33: Row Labels | V33: Sum of Order Value | X33: 2. Using Pivot Tables: Inserted Pivot tables to show total sales by Year & Month
A34: 33 | B34: =Table6[[#This Row],[Initials]] -> D | C34: =Table6[[#This Row],[Last Name Correction]] -> Fenton | D34: Miss | E34: =Table6[[#This Row],[Gender Correction]] -> F | F34: 90 | G34: Sladedale Road | H34: Newnham | I34: 39534 | J34: 60 | K34: E | L34: =VLOOKUP(Portfolio43468[[#This Row],[Product]],ProductName,2) -> Superwossname | M34: =VLOOKUP(K34,ProductName,4)*J34 -> 1200 | N34: =VLOOKUP(K34,ProductName,3)*M34 -> 3732 | O34: =YEAR(I34) -> 2008 | P34: =TEXT(I34,"MMM") -> Mar | R34: 2008 | S34: 1683780.7 | U34: Jan | V34: 419561.25
A35: 34 | B35: =Table6[[#This Row],[Initials]] -> J | C35: =Table6[[#This Row],[Last Name Correction]] -> Blackburn | D35: Mrs | E35: =Table6[[#This Row],[Gender Correction]] -> F | F35: 30 | G35: Falkland Place | H35: Ascot | I35: 39746 | J35: 22 | K35: C1 | L35: =VLOOKUP(Portfolio43468[[#This Row],[Product]],ProductName,2) -> Ultrathing V1 | M35: =VLOOKUP(K35,ProductName,4)*J35 -> 374 | N35: =VLOOKUP(K35,ProductName,3)*M35 -> 744.26 | O35: =YEAR(I35) -> 2008 | P35: =TEXT(I35,"MMM") -> Oct | R35: 2009 | S35: 1520156.9 | U35: Feb | V35: 318432.65 | X35: Note: This Sheet is Password Protected, To unlock this sheet use "qwer" as password
A36: 35 | B36: =Table6[[#This Row],[Initials]] -> C | C36: =Table6[[#This Row],[Last Name Correction]] -> Mcfadden | D36: Miss | E36: =Table6[[#This Row],[Gender Correction]] -> F | F36: 60 | G36: Westdean Close | H36: Ardgay | I36: 39449 | J36: 99 | K36: A1 | L36: =VLOOKUP(Portfolio43468[[#This Row],[Product]],ProductName,2) -> Megawidget S | M36: =VLOOKUP(K36,ProductName,4)*J36 -> 2376 | N36: =VLOOKUP(K36,ProductName,3)*M36 -> 1877.04 | O36: =YEAR(I36) -> 2008 | P36: =TEXT(I36,"MMM") -> Jan | R36: 2010 | S36: 1644229.7 | U36: Mar | V36: 404423.88
A37: 36 | B37: =Table6[[#This Row],[Initials]] -> M | C37: =Table6[[#This Row],[Last Name Correction]] -> Akers | D37: Miss | E37: =Table6[[#This Row],[Gender Correction]] -> F | F37: 30 | G37: Roslyn Avenue | H37: Tidworth | I37: 40442 | J37: 94 | K37: A1 | L37: =VLOOKUP(Portfolio43468[[#This Row],[Product]],ProductName,2) -> Megawidget S | M37: =VLOOKUP(K37,ProductName,4)*J37 -> 2256 | N37: =VLOOKUP(K37,ProductName,3)*M37 -> 1782.24 | O37: =YEAR(I37) -> 2010 | P37: =TEXT(I37,"MMM") -> Sep | R37: Grand Total | S37: 4848167.3 | U37: Apr | V37: 408986.44
A38: 37 | B38: =Table6[[#This Row],[Initials]] -> T | C38: =Table6[[#This Row],[Last Name Correction]] -> Meza | D38: Mrs | E38: =Table6[[#This Row],[Gender Correction]] -> F | F38: 90 | G38: East Mount | H38: Llandinam | I38: 40452 | J38: 3 | K38: B | L38: =VLOOKUP(Portfolio43468[[#This Row],[Product]],ProductName,2) -> Hyperwotsit | M38: =VLOOKUP(K38,ProductName,4)*J38 -> 60 | N38: =VLOOKUP(K38,ProductName,3)*M38 -> 120.6 | O38: =YEAR(I38) -> 2010 | P38: =TEXT(I38,"MMM") -> Oct | U38: May | V38: 443862.81
A39: 38 | B39: =Table6[[#This Row],[Initials]] -> J | C39: =Table6[[#This Row],[Last Name Correction]] -> Johnston | D39: Mrs | E39: =Table6[[#This Row],[Gender Correction]] -> F | F39: 60 | G39: Grainger Street | H39: Christchurch | I39: 39530 | J39: 16 | K39: A1 | L39: =VLOOKUP(Portfolio43468[[#This Row],[Product]],ProductName,2) -> Megawidget S | M39: =VLOOKUP(K39,ProductName,4)*J39 -> 384 | N39: =VLOOKUP(K39,ProductName,3)*M39 -> 303.36 | O39: =YEAR(I39) -> 2008 | P39: =TEXT(I39,"MMM") -> Mar | U39: Jun | V39: 430839.18
A40: 39 | B40: =Table6[[#This Row],[Initials]] -> K | C40: =Table6[[#This Row],[Last Name Correction]] -> Kay | D40: Mrs | E40: =Table6[[#This Row],[Gender Correction]] -> F | F40: 90 | G40: Upper Paget | H40: Cheshire | I40: 40098 | J40: 57 | K40: C4 | L40: =VLOOKUP(Portfolio43468[[#This Row],[Product]],ProductName,2) -> Ultrathing V4 | M40: =VLOOKUP(K40,ProductName,4)*J40 -> 1368 | N40: =VLOOKUP(K40,ProductName,3)*M40 -> 5458.32 | O40: =YEAR(I40) -> 2009 | P40: =TEXT(I40,"MMM") -> Oct | U40: Jul | V40: 416797.24
A41: 40 | B41: =Table6[[#This Row],[Initials]] -> S | C41: =Table6[[#This Row],[Last Name Correction]] -> Baker | D41: Miss | E41: =Table6[[#This Row],[Gender Correction]] -> F | F41: 30 | G41: Claypole Road | H41: Lancaster | I41: 40337 | J41: 44 | K41: C1 | L41: =VLOOKUP(Portfolio43468[[#This Row],[Product]],ProductName,2) -> Ultrathing V1 | M41: =VLOOKUP(K41,ProductName,4)*J41 -> 748 | N41: =VLOOKUP(K41,ProductName,3)*M41 -> 1488.52 | O41: =YEAR(I41) -> 2010 | P41: =TEXT(I41,"MMM") -> Jun | U41: Aug | V41: 389775.04
A42: 41 | B42: =Table6[[#This Row],[Initials]] -> A | C42: =Table6[[#This Row],[Last Name Correction]] -> Montgomery | D42: Miss | E42: =Table6[[#This Row],[Gender Correction]] -> F | F42: 60 | G42: Halsbrook Road | H42: Egremont | I42: 39517 | J42: 73 | K42: A3 | L42: =VLOOKUP(Portfolio43468[[#This Row],[Product]],ProductName,2) -> Megawidget L | M42: =VLOOKUP(K42,ProductName,4)*J42 -> 1752 | N42: =VLOOKUP(K42,ProductName,3)*M42 -> 2785.68 | O42: =YEAR(I42) -> 2008 | P42: =TEXT(I42,"MMM") -> Mar | U42: Sep | V42: 422619.3
A43: 42 | B43: =Table6[[#This Row],[Initials]] -> C | C43: =Table6[[#This Row],[Last Name Correction]] -> Surname | D43: Mrs | E43: =Table6[[#This Row],[Gender Correction]] -> F | F43: 30 | G43: Kevelioc Road | H43: Llangollen | I43: 40165 | J43: 85 | K43: A2 | L43: =VLOOKUP(Portfolio43468[[#This Row],[Product]],ProductName,2) -> Megawidget M | M43: =VLOOKUP(K43,ProductName,4)*J43 -> 2040 | N43: =VLOOKUP(K43,ProductName,3)*M43 -> 2427.6 | O43: =YEAR(I43) -> 2009 | P43: =TEXT(I43,"MMM") -> Dec | U43: Oct | V43: 394335.26
A44: 43 | B44: =Table6[[#This Row],[Initials]] -> M | C44: =Table6[[#This Row],[Last Name Correction]] -> Orozco | D44: Mrs | E44: =Table6[[#This Row],[Gender Correction]] -> F | F44: 60 | G44: Crede Cottages | H44: Cockermouth | I44: 39905 | J44: 41 | K44: C4 | L44: =VLOOKUP(Portfolio43468[[#This Row],[Product]],ProductName,2) -> Ultrathing V4 | M44: =VLOOKUP(K44,ProductName,4)*J44 -> 984 | N44: =VLOOKUP(K44,ProductName,3)*M44 -> 3926.16 | O44: =YEAR(I44) -> 2009 | P44: =TEXT(I44,"MMM") -> Apr | U44: Nov | V44: 410630.94
A45: 44 | B45: =Table6[[#This Row],[Initials]] -> B | C45: =Table6[[#This Row],[Last Name Correction]] -> Joseph | D45: Mrs | E45: =Table6[[#This Row],[Gender Correction]] -> F | F45: 90 | G45: Hanford Close | H45: Torquay | I45: 40074 | J45: 19 | K45: C3 | L45: =VLOOKUP(Portfolio43468[[#This Row],[Product]],ProductName,2) -> Ultrathing V3 | M45: =VLOOKUP(K45,ProductName,4)*J45 -> 456 | N45: =VLOOKUP(K45,ProductName,3)*M45 -> 1591.44 | O45: =YEAR(I45) -> 2009 | P45: =TEXT(I45,"MMM") -> Sep | U45: Dec | V45: 387903.33
A46: 45 | B46: =Table6[[#This Row],[Initials]] -> J | C46: =Table6[[#This Row],[Last Name Correction]] -> Barron | D46: Miss | E46: =Table6[[#This Row],[Gender Correction]] -> F | F46: 30 | G46: Haydon Way | H46: March | I46: 40382 | J46: 22 | K46: D | L46: =VLOOKUP(Portfolio43468[[#This Row],[Product]],ProductName,2) -> Gigastuff | M46: =VLOOKUP(K46,ProductName,4)*J46 -> 396 | N46: =VLOOKUP(K46,ProductName,3)*M46 -> 748.44 | O46: =YEAR(I46) -> 2010 | P46: =TEXT(I46,"MMM") -> Jul | U46: Grand Total | V46: 4848167.3
A47: 46 | B47: =Table6[[#This Row],[Initials]] -> N | C47: =Table6[[#This Row],[Last Name Correction]] -> Cullen | D47: Mrs | E47: =Table6[[#This Row],[Gender Correction]] -> F | F47: 30 | G47: Paragon Place | H47: Fareham | I47: 39587 | J47: 44 | K47: D | L47: =VLOOKUP(Portfolio43468[[#This Row],[Product]],ProductName,2) -> Gigastuff | M47: =VLOOKUP(K47,ProductName,4)*J47 -> 792 | N47: =VLOOKUP(K47,ProductName,3)*M47 -> 1496.88 | O47: =YEAR(I47) -> 2008 | P47: =TEXT(I47,"MMM") -> May
A48: 47 | B48: =Table6[[#This Row],[Initials]] -> B | C48: =Table6[[#This Row],[Last Name Correction]] -> Grove | D48: Miss | E48: =Table6[[#This Row],[Gender Correction]] -> F | F48: 60 | G48: Langdon Place | H48: Hertfordshire | I48: 40510 | J48: 52 | K48: C3 | L48: =VLOOKUP(Portfolio43468[[#This Row],[Product]],ProductName,2) -> Ultrathing V3 | M48: =VLOOKUP(K48,ProductName,4)*J48 -> 1248 | N48: =VLOOKUP(K48,ProductName,3)*M48 -> 4355.52 | O48: =YEAR(I48) -> 2010 | P48: =TEXT(I48,"MMM") -> Nov
A49: 48 | B49: =Table6[[#This Row],[Initials]] -> K | C49: =Table6[[#This Row],[Last Name Correction]] -> Guthrie | D49: Miss | E49: =Table6[[#This Row],[Gender Correction]] -> F | F49: 30 | G49: Power Road | H49: Corsham | I49: 40442 | J49: 54 | K49: E | L49: =VLOOKUP(Portfolio43468[[#This Row],[Product]],ProductName,2) -> Superwossname | M49: =VLOOKUP(K49,ProductName,4)*J49 -> 1080 | N49: =VLOOKUP(K49,ProductName,3)*M49 -> 3358.8 | O49: =YEAR(I49) -> 2010 | P49: =TEXT(I49,"MMM") -> Sep
A50: 49 | B50: =Table6[[#This Row],[Initials]] -> G | C50: =Table6[[#This Row],[Last Name Correction]] -> Greene | D50: Mrs | E50: =Table6[[#This Row],[Gender Correction]] -> F | F50: 60 | G50: Paultons Square | H50: Billericay | I50: 39798 | J50: 86 | K50: A2 | L50: =VLOOKUP(Portfolio43468[[#This Row],[Product]],ProductName,2) -> Megawidget M | M50: =VLOOKUP(K50,ProductName,4)*J50 -> 2064 | N50: =VLOOKUP(K50,ProductName,3)*M50 -> 2456.16 | O50: =YEAR(I50) -> 2008 | P50: =TEXT(I50,"MMM") -> Dec
A51: 50 | B51: =Table6[[#This Row],[Initials]] -> C | C51: =Table6[[#This Row],[Last Name Correction]] -> Parson | D51: Miss | E51: =Table6[[#This Row],[Gender Correction]] -> F | F51: 60 | G51: Trenchard Street | H51: Badminton | I51: 39656 | J51: 34 | K51: B | L51: =VLOOKUP(Portfolio43468[[#This Row],[Product]],ProductName,2) -> Hyperwotsit | M51: =VLOOKUP(K51,ProductName,4)*J51 -> 680 | N51: =VLOOKUP(K51,ProductName,3)*M51 -> 1366.8 | O51: =YEAR(I51) -> 2008 | P51: =TEXT(I51,"MMM") -> Jul
A52: 51 | B52: =Table6[[#This Row],[Initials]] -> J | C52: =Table6[[#This Row],[Last Name Correction]] -> Hancock | D52: Mrs | E52: =Table6[[#This Row],[Gender Correction]] -> F | F52: 60 | G52: College | H52: Henley-In-Arden | I52: 39668 | J52: 54 | K52: E | L52: =VLOOKUP(Portfolio43468[[#This Row],[Product]],ProductName,2) -> Superwossname | M52: =VLOOKUP(K52,ProductName,4)*J52 -> 1080 | N52: =VLOOKUP(K52,ProductName,3)*M52 -> 3358.8 | O52: =YEAR(I52) -> 2008 | P52: =TEXT(I52,"MMM") -> Aug
A53: 52 | B53: =Table6[[#This Row],[Initials]] -> P | C53: =Table6[[#This Row],[Last Name Correction]] -> Hancock | D53: Mrs | E53: =Table6[[#This Row],[Gender Correction]] -> F | F53: 60 | G53: Bridson Street | H53: Oban | I53: 40399 | J53: 84 | K53: E | L53: =VLOOKUP(Portfolio43468[[#This Row],[Product]],ProductName,2) -> Superwossname | M53: =VLOOKUP(K53,ProductName,4)*J53 -> 1680 | N53: =VLOOKUP(K53,ProductName,3)*M53 -> 5224.8 | O53: =YEAR(I53) -> 2010 | P53: =TEXT(I53,"MMM") -> Aug
A54: 53 | B54: =Table6[[#This Row],[Initials]] -> E | C54: =Table6[[#This Row],[Last Name Correction]] -> Hart | D54: Miss | E54: =Table6[[#This Row],[Gender Correction]] -> F | F54: 30 | G54: Bowl Court | H54: Dalbeattie | I54: 40221 | J54: 46 | K54: C3 | L54: =VLOOKUP(Portfolio43468[[#This Row],[Product]],ProductName,2) -> Ultrathing V3 | M54: =VLOOKUP(K54,ProductName,4)*J54 -> 1104 | N54: =VLOOKUP(K54,ProductName,3)*M54 -> 3852.96 | O54: =YEAR(I54) -> 2010 | P54: =TEXT(I54,"MMM") -> Feb
A55: 54 | B55: =Table6[[#This Row],[Initials]] -> F | C55: =Table6[[#This Row],[Last Name Correction]] -> Sadler | D55: Miss | E55: =Table6[[#This Row],[Gender Correction]] -> F | F55: 30 | G55: Lyons Inn | H55: Builth Wells | I55: 40126 | J55: 72 | K55: C4 | L55: =VLOOKUP(Portfolio43468[[#This Row],[Product]],ProductName,2) -> Ultrathing V4 | M55: =VLOOKUP(K55,ProductName,4)*J55 -> 1728 | N55: =VLOOKUP(K55,ProductName,3)*M55 -> 6894.72 | O55: =YEAR(I55) -> 2009 | P55: =TEXT(I55,"MMM") -> Nov
A56: 55 | B56: =Table6[[#This Row],[Initials]] -> D | C56: =Table6[[#This Row],[Last Name Correction]] -> Finch | D56: Miss | E56: =Table6[[#This Row],[Gender Correction]] -> F | F56: 60 | G56: Bells Buildings | H56: Badminton | I56: 39465 | J56: 27 | K56: C4 | L56: =VLOOKUP(Portfolio43468[[#This Row],[Product]],ProductName,2) -> Ultrathing V4 | M56: =VLOOKUP(K56,ProductName,4)*J56 -> 648 | N56: =VLOOKUP(K56,ProductName,3)*M56 -> 2585.52 | O56: =YEAR(I56) -> 2008 | P56: =TEXT(I56,"MMM") -> Jan
A57: 56 | B57: =Table6[[#This Row],[Initials]] -> G | C57: =Table6[[#This Row],[Last Name Correction]] -> Flores | D57: Mrs | E57: =Table6[[#This Row],[Gender Correction]] -> F | F57: 90 | G57: Sotheron Road | H57: Bideford | I57: 39809 | J57: 97 | K57: C2 | L57: =VLOOKUP(Portfolio43468[[#This Row],[Product]],ProductName,2) -> Ultrathing V2 | M57: =VLOOKUP(K57,ProductName,4)*J57 -> 1940 | N57: =VLOOKUP(K57,ProductName,3)*M57 -> 5800.6 | O57: =YEAR(I57) -> 2008 | P57: =TEXT(I57,"MMM") -> Dec
A58: 57 | B58: =Table6[[#This Row],[Initials]] -> D | C58: =Table6[[#This Row],[Last Name Correction]] -> Darby | D58: Mrs | E58: =Table6[[#This Row],[Gender Correction]] -> F | F58: 30 | G58: Old Dover | H58: Halesworth | I58: 40492 | J58: 68 | K58: C3 | L58: =VLOOKUP(Portfolio43468[[#This Row],[Product]],ProductName,2) -> Ultrathing V3 | M58: =VLOOKUP(K58,ProductName,4)*J58 -> 1632 | N58: =VLOOKUP(K58,ProductName,3)*M58 -> 5695.68 | O58: =YEAR(I58) -> 2010 | P58: =TEXT(I58,"MMM") -> Nov
... A1987: 2000 | B1987: =Table6[[#This Row],[Initials]] -> G | C1987: =Table6[[#This Row],[Last Name Correction]] -> Guy | D1987: Mr | E1987: =Table6[[#This Row],[Gender Correction]] -> M | F1987: 60 | G1987: Wansbeck Road | H1987: Ledbury | I1987: 40301 | J1987: 58 | K1987: D | L1987: =VLOOKUP(Portfolio43468[[#This Row],[Product]],ProductName,2) -> Gigastuff | M1987: =VLOOKUP(K1987,ProductName,4)*J1987 -> 1044 | N1987: =VLOOKUP(K1987,ProductName,3)*M1987 -> 1973.16 | O1987: =YEAR(I1987) -> 2010 | P1987: =TEXT(I1987,"MMM") -> May

Sheet Task 4.4
A1: ID | B1: First Name | C1: Last Name | D1: Title | E1: Gender | F1: Credit | G1: Street | H1: Town | I1: Postal Code | J1: Order Date | K1: Quantity | L1: Product | M1: Product Name | N1: Order Quantity | O1: Order Value | P1: Year | Q1: Month
A2: 1 | B2: =Portfolio43468[[#This Row],[First Name]] -> N | C2: =Portfolio43468[[#This Row],[Last Name]] -> Camp | D2: Mrs | E2: =Portfolio43468[[#This Row],[Gender]] -> F | F2: 60 | G2: Rosmore Road | H2: Berkeley | I2: =INDEX('Postal Codes 1'!$C$2:$C$1540,MATCH(H2,'Postal Codes 1'!$B$2:$B$1540,0)) -> GL | J2: 39988 | K2: 13 | L2: A1 | M2: =Portfolio43468[[#This Row],[Product Name]] -> Megawidget S | N2: =Portfolio43468[[#This Row],[Order Quantity]] -> 312 | O2: =Portfolio43468[[#This Row],[Order Value]] -> 246.48 | P2: =YEAR(J2) -> 2009 | Q2: =TEXT(J2,"MMM") -> Jun | S2: STEPS
A3: 2 | B3: =Portfolio43468[[#This Row],[First Name]] -> E | C3: =Portfolio43468[[#This Row],[Last Name]] -> Dorsey | D3: Mrs | E3: =Portfolio43468[[#This Row],[Gender]] -> F | F3: 90 | G3: Roxwell Road | H3: Glossop | I3: =INDEX('Postal Codes 1'!$C$2:$C$1540,MATCH(H3,'Postal Codes 1'!$B$2:$B$1540,0)) -> SK | J3: 39770 | K3: 14 | L3: C3 | M3: =Portfolio43468[[#This Row],[Product Name]] -> Ultrathing V3 | N3: =Portfolio43468[[#This Row],[Order Quantity]] -> 336 | O3: =Portfolio43468[[#This Row],[Order Value]] -> 1172.64 | P3: =YEAR(J3) -> 2008 | Q3: =TEXT(J3,"MMM") -> Nov | S3: Found a list of UK postal codes and imported it to a new sheet called "Postal Codes 1"
A4: 3 | B4: =Portfolio43468[[#This Row],[First Name]] -> A | C4: =Portfolio43468[[#This Row],[Last Name]] -> Devine | D4: Mrs | E4: =Portfolio43468[[#This Row],[Gender]] -> F | F4: 60 | G4: Ashbury Place | H4: Immingham | I4: =INDEX('Postal Codes 1'!$C$2:$C$1540,MATCH(H4,'Postal Codes 1'!$B$2:$B$1540,0)) -> DN | J4: 39895 | K4: 23 | L4: E | M4: =Portfolio43468[[#This Row],[Product Name]] -> Superwossname | N4: =Portfolio43468[[#This Row],[Order Quantity]] -> 460 | O4: =Portfolio43468[[#This Row],[Order Value]] -> 1430.6 | P4: =YEAR(J4) -> 2009 | Q4: =TEXT(J4,"MMM") -> Mar
A5: 4 | B5: =Portfolio43468[[#This Row],[First Name]] -> N | C5: =Portfolio43468[[#This Row],[Last Name]] -> Washington | D5: Miss | E5: =Portfolio43468[[#This Row],[Gender]] -> F | F5: 60 | G5: Grafton Road | H5: Broadstone | I5: =INDEX('Postal Codes 1'!$C$2:$C$1540,MATCH(H5,'Postal Codes 1'!$B$2:$B$1540,0)) -> BH | J5: 39830 | K5: 79 | L5: E | M5: =Portfolio43468[[#This Row],[Product Name]] -> Superwossname | N5: =Portfolio43468[[#This Row],[Order Quantity]] -> 1580 | O5: =Portfolio43468[[#This Row],[Order Value]] -> 4913.8 | P5: =YEAR(J5) -> 2009 | Q5: =TEXT(J5,"MMM") -> Jan | S5: Added a New column"Postal Code" to show the correct Postal code Region
A6: 5 | B6: =Portfolio43468[[#This Row],[First Name]] -> S | C6: =Portfolio43468[[#This Row],[Last Name]] -> Hedrick | D6: Miss | E6: =Portfolio43468[[#This Row],[Gender]] -> F | F6: 60 | G6: Beechdale Road | H6: Port Talbot | I6: =INDEX('Postal Codes 1'!$C$2:$C$1540,MATCH(H6,'Postal Codes 1'!$B$2:$B$1540,0)) -> SA | J6: 39988 | K6: 44 | L6: C3 | M6: =Portfolio43468[[#This Row],[Product Name]] -> Ultrathing V3 | N6: =Portfolio43468[[#This Row],[Order Quantity]] -> 1056 | O6: =Portfolio43468[[#This Row],[Order Value]] -> 3685.44 | P6: =YEAR(J6) -> 2009 | Q6: =TEXT(J6,"MMM") -> Jun | S6: Used the INDEX function to find the right code for each town.
A7: 6 | B7: =Portfolio43468[[#This Row],[First Name]] -> V | C7: =Portfolio43468[[#This Row],[Last Name]] -> Lundy | D7: Miss | E7: =Portfolio43468[[#This Row],[Gender]] -> F | F7: 90 | G7: Katherine Gardens | H7: Ardgay | I7: =INDEX('Postal Codes 1'!$C$2:$C$1540,MATCH(H7,'Postal Codes 1'!$B$2:$B$1540,0)) -> IV | J7: 40316 | K7: 37 | L7: A3 | M7: =Portfolio43468[[#This Row],[Product Name]] -> Megawidget L | N7: =Portfolio43468[[#This Row],[Order Quantity]] -> 888 | O7: =Portfolio43468[[#This Row],[Order Value]] -> 1411.92 | P7: =YEAR(J7) -> 2010 | Q7: =TEXT(J7,"MMM") -> May | S7: Formula: =INDEX('Postal Codes 1'!$C$2:$C$1540,MATCH(H2,'Postal Codes 1'!$B$2:$B$1540,0))
A8: 7 | B8: =Portfolio43468[[#This Row],[First Name]] -> V | C8: =Portfolio43468[[#This Row],[Last Name]] -> Frost | D8: Mrs | E8: =Portfolio43468[[#This Row],[Gender]] -> F | F8: 30 | G8: Ross Way | H8: Solihull | I8: =INDEX('Postal Codes 1'!$C$2:$C$1540,MATCH(H8,'Postal Codes 1'!$B$2:$B$1540,0)) -> B | J8: 40202 | K8: 12 | L8: C2 | M8: =Portfolio43468[[#This Row],[Product Name]] -> Ultrathing V2 | N8: =Portfolio43468[[#This Row],[Order Quantity]] -> 240 | O8: =Portfolio43468[[#This Row],[Order Value]] -> 717.6 | P8: =YEAR(J8) -> 2010 | Q8: =TEXT(J8,"MMM") -> Jan
A9: 8 | B9: =Portfolio43468[[#This Row],[First Name]] -> R | C9: =Portfolio43468[[#This Row],[Last Name]] -> Woods | D9: Mrs | E9: =Portfolio43468[[#This Row],[Gender]] -> F | F9: 30 | G9: Artisans Dwellings | H9: Tring | I9: =INDEX('Postal Codes 1'!$C$2:$C$1540,MATCH(H9,'Postal Codes 1'!$B$2:$B$1540,0)) -> HP | J9: 40497 | K9: 55 | L9: C1 | M9: =Portfolio43468[[#This Row],[Product Name]] -> Ultrathing V1 | N9: =Portfolio43468[[#This Row],[Order Quantity]] -> 935 | O9: =Portfolio43468[[#This Row],[Order Value]] -> 1860.65 | P9: =YEAR(J9) -> 2010 | Q9: =TEXT(J9,"MMM") -> Nov
A10: 9 | B10: =Portfolio43468[[#This Row],[First Name]] -> K | C10: =Portfolio43468[[#This Row],[Last Name]] -> Navarro | D10: Mrs | E10: =Portfolio43468[[#This Row],[Gender]] -> F | F10: 30 | G10: Rhoda Street | H10: St. Ives | I10: =INDEX('Postal Codes 1'!$C$2:$C$1540,MATCH(H10,'Postal Codes 1'!$B$2:$B$1540,0)) -> PE | J10: 39938 | K10: 10 | L10: C3 | M10: =Portfolio43468[[#This Row],[Product Name]] -> Ultrathing V3 | N10: =Portfolio43468[[#This Row],[Order Quantity]] -> 240 | O10: =Portfolio43468[[#This Row],[Order Value]] -> 837.6 | P10: =YEAR(J10) -> 2009 | Q10: =TEXT(J10,"MMM") -> May | S10: Note: This Sheet is Password Protected, To unlock this sheet use "qwer" as password
A11: 10 | B11: =Portfolio43468[[#This Row],[First Name]] -> M | C11: =Portfolio43468[[#This Row],[Last Name]] -> Anthony | D11: Miss | E11: =Portfolio43468[[#This Row],[Gender]] -> F | F11: 90 | G11: Iceland Road | H11: Campbeltown | I11: =INDEX('Postal Codes 1'!$C$2:$C$1540,MATCH(H11,'Postal Codes 1'!$B$2:$B$1540,0)) -> PA | J11: 40466 | K11: 76 | L11: A2 | M11: =Portfolio43468[[#This Row],[Product Name]] -> Megawidget M | N11: =Portfolio43468[[#This Row],[Order Quantity]] -> 1824 | O11: =Portfolio43468[[#This Row],[Order Value]] -> 2170.56 | P11: =YEAR(J11) -> 2010 | Q11: =TEXT(J11,"MMM") -> Oct
A12: 11 | B12: =Portfolio43468[[#This Row],[First Name]] -> S | C12: =Portfolio43468[[#This Row],[Last Name]] -> Roland | D12: Mrs | E12: =Portfolio43468[[#This Row],[Gender]] -> F | F12: 90 | G12: Samels Court | H12: Newbridge | I12: =INDEX('Postal Codes 1'!$C$2:$C$1540,MATCH(H12,'Postal Codes 1'!$B$2:$B$1540,0)) -> EH | J12: 40031 | K12: 28 | L12: C2 | M12: =Portfolio43468[[#This Row],[Product Name]] -> Ultrathing V2 | N12: =Portfolio43468[[#This Row],[Order Quantity]] -> 560 | O12: =Portfolio43468[[#This Row],[Order Value]] -> 1674.4 | P12: =YEAR(J12) -> 2009 | Q12: =TEXT(J12,"MMM") -> Aug
A13: 12 | B13: =Portfolio43468[[#This Row],[First Name]] -> Y | C13: =Portfolio43468[[#This Row],[Last Name]] -> Culver | D13: Miss | E13: =Portfolio43468[[#This Row],[Gender]] -> F | F13: 60 | G13: Garratt Green | H13: London | I13: =INDEX('Postal Codes 1'!$C$2:$C$1540,MATCH(H13,'Postal Codes 1'!$B$2:$B$1540,0)) -> E | J13: 39965 | K13: 41 | L13: A2 | M13: =Portfolio43468[[#This Row],[Product Name]] -> Megawidget M | N13: =Portfolio43468[[#This Row],[Order Quantity]] -> 984 | O13: =Portfolio43468[[#This Row],[Order Value]] -> 1170.96 | P13: =YEAR(J13) -> 2009 | Q13: =TEXT(J13,"MMM") -> Jun
A14: 13 | B14: =Portfolio43468[[#This Row],[First Name]] -> M | C14: =Portfolio43468[[#This Row],[Last Name]] -> Doran | D14: Miss | E14: =Portfolio43468[[#This Row],[Gender]] -> F | F14: 90 | G14: High St | H14: Caldicot | I14: =INDEX('Postal Codes 1'!$C$2:$C$1540,MATCH(H14,'Postal Codes 1'!$B$2:$B$1540,0)) -> NP | J14: 39516 | K14: 48 | L14: B | M14: =Portfolio43468[[#This Row],[Product Name]] -> Hyperwotsit | N14: =Portfolio43468[[#This Row],[Order Quantity]] -> 960 | O14: =Portfolio43468[[#This Row],[Order Value]] -> 1929.6 | P14: =YEAR(J14) -> 2008 | Q14: =TEXT(J14,"MMM") -> Mar
A15: 14 | B15: =Portfolio43468[[#This Row],[First Name]] -> L | C15: =Portfolio43468[[#This Row],[Last Name]] -> Richards | D15: Prof | E15: =Portfolio43468[[#This Row],[Gender]] -> F | F15: 90 | G15: Brackenfield Close | H15: Broseley | I15: =INDEX('Postal Codes 1'!$C$2:$C$1540,MATCH(H15,'Postal Codes 1'!$B$2:$B$1540,0)) -> TF | J15: 39665 | K15: 34 | L15: C4 | M15: =Portfolio43468[[#This Row],[Product Name]] -> Ultrathing V4 | N15: =Portfolio43468[[#This Row],[Order Quantity]] -> 816 | O15: =Portfolio43468[[#This Row],[Order Value]] -> 3255.84 | P15: =YEAR(J15) -> 2008 | Q15: =TEXT(J15,"MMM") -> Aug
A16: 15 | B16: =Portfolio43468[[#This Row],[First Name]] -> M | C16: =Portfolio43468[[#This Row],[Last Name]] -> Wright | D16: Mrs | E16: =Portfolio43468[[#This Row],[Gender]] -> F | F16: 60 | G16: Bearstead Rise | H16: Y Felinheli | I16: =INDEX('Postal Codes 1'!$C$2:$C$1540,MATCH(H16,'Postal Codes 1'!$B$2:$B$1540,0)) -> LL | J16: 40337 | K16: 57 | L16: C4 | M16: =Portfolio43468[[#This Row],[Product Name]] -> Ultrathing V4 | N16: =Portfolio43468[[#This Row],[Order Quantity]] -> 1368 | O16: =Portfolio43468[[#This Row],[Order Value]] -> 5458.32 | P16: =YEAR(J16) -> 2010 | Q16: =TEXT(J16,"MMM") -> Jun
A17: 16 | B17: =Portfolio43468[[#This Row],[First Name]] -> B | C17: =Portfolio43468[[#This Row],[Last Name]] -> Vasquez | D17: Mrs | E17: =Portfolio43468[[#This Row],[Gender]] -> F | F17: 30 | G17: Baker Road | H17: Trowbridge | I17: =INDEX('Postal Codes 1'!$C$2:$C$1540,MATCH(H17,'Postal Codes 1'!$B$2:$B$1540,0)) -> BA | J17: 40532 | K17: 59 | L17: E | M17: =Portfolio43468[[#This Row],[Product Name]] -> Superwossname | N17: =Portfolio43468[[#This Row],[Order Quantity]] -> 1180 | O17: =Portfolio43468[[#This Row],[Order Value]] -> 3669.8 | P17: =YEAR(J17) -> 2010 | Q17: =TEXT(J17,"MMM") -> Dec
A18: 17 | B18: =Portfolio43468[[#This Row],[First Name]] -> E | C18: =Portfolio43468[[#This Row],[Last Name]] -> Butler | D18: Miss | E18: =Portfolio43468[[#This Row],[Gender]] -> F | F18: 30 | G18: Telford Close | H18: Isles Of Scilly | I18: =INDEX('Postal Codes 1'!$C$2:$C$1540,MATCH(H18,'Postal Codes 1'!$B$2:$B$1540,0)) -> TR | J18: 40271 | K18: 84 | L18: C1 | M18: =Portfolio43468[[#This Row],[Product Name]] -> Ultrathing V1 | N18: =Portfolio43468[[#This Row],[Order Quantity]] -> 1428 | O18: =Portfolio43468[[#This Row],[Order Value]] -> 2841.72 | P18: =YEAR(J18) -> 2010 | Q18: =TEXT(J18,"MMM") -> Apr
A19: 18 | B19: =Portfolio43468[[#This Row],[First Name]] -> I | C19: =Portfolio43468[[#This Row],[Last Name]] -> Hutchinson | D19: Ms | E19: =Portfolio43468[[#This Row],[Gender]] -> F | F19: 30 | G19: Queens Buildings | H19: Kilmacolm | I19: =INDEX('Postal Codes 1'!$C$2:$C$1540,MATCH(H19,'Postal Codes 1'!$B$2:$B$1540,0)) -> PA | J19: 40183 | K19: 39 | L19: C4 | M19: =Portfolio43468[[#This Row],[Product Name]] -> Ultrathing V4 | N19: =Portfolio43468[[#This Row],[Order Quantity]] -> 936 | O19: =Portfolio43468[[#This Row],[Order Value]] -> 3734.64 | P19: =YEAR(J19) -> 2010 | Q19: =TEXT(J19,"MMM") -> Jan
A20: 19 | B20: =Portfolio43468[[#This Row],[First Name]] -> W | C20: =Portfolio43468[[#This Row],[Last Name]] -> Cabrera | D20: Miss | E20: =Portfolio43468[[#This Row],[Gender]] -> F | F20: 90 | G20: Havelock Cottages | H20: Bridgwater | I20: =INDEX('Postal Codes 1'!$C$2:$C$1540,MATCH(H20,'Postal Codes 1'!$B$2:$B$1540,0)) -> TA | J20: 40381 | K20: 54 | L20: A1 | M20: =Portfolio43468[[#This Row],[Product Name]] -> Megawidget S | N20: =Portfolio43468[[#This Row],[Order Quantity]] -> 1296 | O20: =Portfolio43468[[#This Row],[Order Value]] -> 1023.84 | P20: =YEAR(J20) -> 2010 | Q20: =TEXT(J20,"MMM") -> Jul
A21: 20 | B21: =Portfolio43468[[#This Row],[First Name]] -> C | C21: =Portfolio43468[[#This Row],[Last Name]] -> Walsh | D21: Mrs | E21: =Portfolio43468[[#This Row],[Gender]] -> F | F21: 90 | G21: Huntingdon Gardens | H21: Essex | I21: =INDEX('Postal Codes 1'!$C$2:$C$1540,MATCH(H21,'Postal Codes 1'!$B$2:$B$1540,0)) -> CB | J21: 40469 | K21: 33 | L21: C2 | M21: =Portfolio43468[[#This Row],[Product Name]] -> Ultrathing V2 | N21: =Portfolio43468[[#This Row],[Order Quantity]] -> 660 | O21: =Portfolio43468[[#This Row],[Order Value]] -> 1973.4 | P21: =YEAR(J21) -> 2010 | Q21: =TEXT(J21,"MMM") -> Oct
A22: 21 | B22: =Portfolio43468[[#This Row],[First Name]] -> J | C22: =Portfolio43468[[#This Row],[Last Name]] -> Farley | D22: Mrs | E22: =Portfolio43468[[#This Row],[Gender]] -> F | F22: 60 | G22: Embankment Gardens | H22: Badminton | I22: =INDEX('Postal Codes 1'!$C$2:$C$1540,MATCH(H22,'Postal Codes 1'!$B$2:$B$1540,0)) -> GL | J22: 39587 | K22: 84 | L22: C2 | M22: =Portfolio43468[[#This Row],[Product Name]] -> Ultrathing V2 | N22: =Portfolio43468[[#This Row],[Order Quantity]] -> 1680 | O22: =Portfolio43468[[#This Row],[Order Value]] -> 5023.2 | P22: =YEAR(J22) -> 2008 | Q22: =TEXT(J22,"MMM") -> May
... A1987: 2000 | B1987: =Portfolio43468[[#This Row],[First Name]] -> G | C1987: =Portfolio43468[[#This Row],[Last Name]] -> Guy | D1987: Mr | E1987: =Portfolio43468[[#This Row],[Gender]] -> M | F1987: 60 | G1987: Wansbeck Road | H1987: Ledbury | I1987: =INDEX('Postal Codes 1'!$C$2:$C$1540,MATCH(H1987,'Postal Codes 1'!$B$2:$B$1540,0)) -> HR | J1987: 40301 | K1987: 58 | L1987: D | M1987: =Portfolio43468[[#This Row],[Product Name]] -> Gigastuff | N1987: =Portfolio43468[[#This Row],[Order Quantity]] -> 1044 | O1987: =Portfolio43468[[#This Row],[Order Value]] -> 1973.16 | P1987: =YEAR(J1987) -> 2010 | Q1987: =TEXT(J1987,"MMM") -> May

Sheet Postal Codes 1
B1: TOWN | C1: AREA
B2: Essex | C2: CB | E2: Note: This Sheet is Password Protected, To unlock this sheet use "qwer" as password
B3: Aberdeenshire | C3: AB
B4: Avon | C4: CV
B5: Berkshire | C5: RG
B6: Buckinghamshire | C6: HP
B7: Cambridgeshire | C7: CB
B8: Cheshire | C8: CH
B9: Cleveland | C9: TS
B10: Cornwall | C10: TR
B11: County Antrim | C11: BT
B12: County Down | C12: BT
B13: County Durham | C13: DH
B14: County Fermanagh | C14: BT
... B1540: Thirsk | C1540: YO

Sheet Postal Codes 2
A1: Town
A2: Berkeley | B2: =VLOOKUP(A2,test,2,FALSE) -> GL
A3: Glossop | B3: =VLOOKUP(A3,test,2,FALSE) -> SK
A4: Immingham | B4: =VLOOKUP(A4,test,2,FALSE) -> DN
A5: Broadstone | B5: =VLOOKUP(A5,test,2,FALSE) -> BH
A6: Port Talbot | B6: =VLOOKUP(A6,test,2,FALSE) -> SA
A7: Ardgay | B7: =VLOOKUP(A7,test,2,FALSE) -> IV
A8: Solihull | B8: =VLOOKUP(A8,test,2,FALSE) -> B
A9: Tring | B9: =VLOOKUP(A9,test,2,FALSE) -> HP
A10: St. Ives | B10: =VLOOKUP(A10,test,2,FALSE) -> PE
A11: Campbeltown | B11: =VLOOKUP(A11,test,2,FALSE) -> PA
A12: Newbridge | B12: =VLOOKUP(A12,test,2,FALSE) -> EH
A13: London | B13: =VLOOKUP(A13,test,2,FALSE) -> E
... A28: Downham Market | B28: =VLOOKUP(A28,test,2,FALSE) -> PE
